{
  "month": 20,
  "count": 153,
  "actions": [
    {
      "agent": "EDU",
      "size": "S",
      "footprint_slots": [
        "s_11"
      ],
      "lp_norm": 0.6356598004044915,
      "cost": 1637.0,
      "reward": 289.0,
      "prestige": 0.2,
      "score": 0.059080626052254163
    },
    {
      "agent": "EDU",
      "size": "S",
      "footprint_slots": [
        "s_64"
      ],
      "lp_norm": 0.6022468757335105,
      "cost": 1604.0,
      "reward": 289.0,
      "prestige": 0.2,
      "score": 0.06052104508324499
    },
    {
      "agent": "EDU",
      "size": "S",
      "footprint_slots": [
        "s_0"
      ],
      "lp_norm": 0.3756127885848022,
      "cost": 1284.0,
      "reward": 236.0,
      "prestige": 0.2,
      "score": 0.029060173349130136
    },
    {
      "agent": "EDU",
      "size": "S",
      "footprint_slots": [
        "s_37"
      ],
      "lp_norm": 0.5730137609877954,
      "cost": 1582.0,
      "reward": 287.0,
      "prestige": 0.2,
      "score": 0.05976703872295318
    },
    {
      "agent": "EDU",
      "size": "S",
      "footprint_slots": [
        "s_4"
      ],
      "lp_norm": 0.3610941999307371,
      "cost": 1262.0,
      "reward": 237.0,
      "prestige": 0.2,
      "score": 0.030877595560266882
    },
    {
      "agent": "EDU",
      "size": "S",
      "footprint_slots": [
        "s_80"
      ],
      "lp_norm": 0.6563306527526704,
      "cost": 1559.0,
      "reward": 246.0,
      "prestige": 0.2,
      "score": 0.02562810999563509
    },
    {
      "agent": "EDU",
      "size": "S",
      "footprint_slots": [
        "s_16"
      ],
      "lp_norm": 0.4452131332452116,
      "cost": 1350.0,
      "reward": 238.0,
      "prestige": 0.2,
      "score": 0.027893621001434186
    },
    {
      "agent": "EDU",
      "size": "S",
      "footprint_slots": [
        "s_12"
      ],
      "lp_norm": 0.536310686040433,
      "cost": 1538.0,
      "reward": 285.0,
      "prestige": 0.2,
      "score": 0.059973311716655237
    },
    {
      "agent": "EDU",
      "size": "S",
      "footprint_slots": [
        "s_14"
      ],
      "lp_norm": 0.5145651173741638,
      "cost": 1516.0,
      "reward": 285.0,
      "prestige": 0.2,
      "score": 0.06093359107064912
    },
    {
      "agent": "EDU",
      "size": "S",
      "footprint_slots": [
        "s_28"
      ],
      "lp_norm": 0.6212639227037201,
      "cost": 1626.0,
      "reward": 290.0,
      "prestige": 0.2,
      "score": 0.060417908586393954
    },
    {
      "agent": "EDU",
      "size": "S",
      "footprint_slots": [
        "s_19"
      ],
      "lp_norm": 0.4235472918721448,
      "cost": 1328.0,
      "reward": 237.0,
      "prestige": 0.2,
      "score": 0.027996757498285212
    },
    {
      "agent": "EDU",
      "size": "S",
      "footprint_slots": [
        "s_79"
      ],
      "lp_norm": 0.5973426126761566,
      "cost": 1504.0,
      "reward": 244.0,
      "prestige": 0.2,
      "score": 0.026314522666334102
    },
    {
      "agent": "EDU",
      "size": "S",
      "footprint_slots": [
        "s_24"
      ],
      "lp_norm": 0.5205655042901448,
      "cost": 1427.0,
      "reward": 241.0,
      "prestige": 0.2,
      "score": 0.027104071833884143
    },
    {
      "agent": "EDU",
      "size": "S",
      "footprint_slots": [
        "s_8"
      ],
      "lp_norm": 0.40117801727205205,
      "cost": 1306.0,
      "reward": 239.0,
      "prestige": 0.2,
      "score": 0.03067132256656482
    },
    {
      "agent": "EDU",
      "size": "S",
      "footprint_slots": [
        "s_20"
      ],
      "lp_norm": 0.5253224084807169,
      "cost": 1427.0,
      "reward": 240.0,
      "prestige": 0.2,
      "score": 0.02624692897674128
    },
    {
      "agent": "EDU",
      "size": "S",
      "footprint_slots": [
        "s_82"
      ],
      "lp_norm": 0.6833946118411781,
      "cost": 1592.0,
      "reward": 246.0,
      "prestige": 0.2,
      "score": 0.024187690964644258
    },
    {
      "agent": "EDU",
      "size": "S",
      "footprint_slots": [
        "s_29"
      ],
      "lp_norm": 0.5607234170649145,
      "cost": 1560.0,
      "reward": 287.0,
      "prestige": 0.2,
      "score": 0.06072731807694706
    },
    {
      "agent": "EDU",
      "size": "S",
      "footprint_slots": [
        "s_30"
      ],
      "lp_norm": 0.618251079311038,
      "cost": 1626.0,
      "reward": 290.0,
      "prestige": 0.2,
      "score": 0.060417908586393954
    },
    {
      "agent": "EDU",
      "size": "S",
      "footprint_slots": [
        "s_10"
      ],
      "lp_norm": 0.5355614348129698,
      "cost": 1538.0,
      "reward": 285.0,
      "prestige": 0.2,
      "score": 0.059973311716655237
    },
    {
      "agent": "EDU",
      "size": "S",
      "footprint_slots": [
        "s_1"
      ],
      "lp_norm": 0.43284247391179026,
      "cost": 1339.0,
      "reward": 239.0,
      "prestige": 0.2,
      "score": 0.029230903535573984
    },
    {
      "agent": "EDU",
      "size": "S",
      "footprint_slots": [
        "s_7"
      ],
      "lp_norm": 0.34234720347939307,
      "cost": 1251.0,
      "reward": 237.0,
      "prestige": 0.2,
      "score": 0.031357735237263824
    },
    {
      "agent": "EDU",
      "size": "S",
      "footprint_slots": [
        "s_34"
      ],
      "lp_norm": 0.5548988764824909,
      "cost": 1560.0,
      "reward": 287.0,
      "prestige": 0.2,
      "score": 0.06072731807694706
    },
    {
      "agent": "EDU",
      "size": "S",
      "footprint_slots": [
        "s_22"
      ],
      "lp_norm": 0.3946067049739341,
      "cost": 1306.0,
      "reward": 237.0,
      "prestige": 0.2,
      "score": 0.028957036852279103
    },
    {
      "agent": "EDU",
      "size": "S",
      "footprint_slots": [
        "s_15"
      ],
      "lp_norm": 0.5720894196601226,
      "cost": 1571.0,
      "reward": 287.0,
      "prestige": 0.2,
      "score": 0.06024717839995012
    },
    {
      "agent": "EDU",
      "size": "S",
      "footprint_slots": [
        "s_295"
      ],
      "lp_norm": 0.4985645829264926,
      "cost": 1505.0,
      "reward": 285.0,
      "prestige": 0.2,
      "score": 0.06141373074764606
    },
    {
      "agent": "EDU",
      "size": "S",
      "footprint_slots": [
        "s_21"
      ],
      "lp_norm": 0.5658460187630443,
      "cost": 1471.0,
      "reward": 242.0,
      "prestige": 0.2,
      "score": 0.026040655983039222
    },
    {
      "agent": "EDU",
      "size": "S",
      "footprint_slots": [
        "s_71"
      ],
      "lp_norm": 0.49041502310587415,
      "cost": 1394.0,
      "reward": 242.0,
      "prestige": 0.2,
      "score": 0.029401633722017834
    },
    {
      "agent": "EDU",
      "size": "S",
      "footprint_slots": [
        "s_83"
      ],
      "lp_norm": 0.712732871809159,
      "cost": 1614.0,
      "reward": 246.0,
      "prestige": 0.2,
      "score": 0.023227411610650367
    },
    {
      "agent": "EDU",
      "size": "S",
      "footprint_slots": [
        "s_2"
      ],
      "lp_norm": 0.5808091889303625,
      "cost": 1582.0,
      "reward": 289.0,
      "prestige": 0.2,
      "score": 0.06148132443723889
    },
    {
      "agent": "EDU",
      "size": "S",
      "footprint_slots": [
        "s_5"
      ],
      "lp_norm": 0.4181704815352727,
      "cost": 1328.0,
      "reward": 238.0,
      "prestige": 0.2,
      "score": 0.028853900355428074
    },
    {
      "agent": "EDU",
      "size": "S",
      "footprint_slots": [
        "s_32"
      ],
      "lp_norm": 0.6618105880510332,
      "cost": 1670.0,
      "reward": 291.0,
      "prestige": 0.2,
      "score": 0.05935449273554904
    },
    {
      "agent": "EDU",
      "size": "S",
      "footprint_slots": [
        "s_13"
      ],
      "lp_norm": 0.5943227411168474,
      "cost": 1593.0,
      "reward": 288.0,
      "prestige": 0.2,
      "score": 0.06014404190309909
    },
    {
      "agent": "EDU",
      "size": "S",
      "footprint_slots": [
        "s_27"
      ],
      "lp_norm": 0.5622849885329231,
      "cost": 1571.0,
      "reward": 287.0,
      "prestige": 0.2,
      "score": 0.06024717839995012
    },
    {
      "agent": "EDU",
      "size": "S",
      "footprint_slots": [
        "s_23"
      ],
      "lp_norm": 0.4684078771266487,
      "cost": 1372.0,
      "reward": 240.0,
      "prestige": 0.2,
      "score": 0.028647627361726005
    },
    {
      "agent": "EDU",
      "size": "S",
      "footprint_slots": [
        "s_9"
      ],
      "lp_norm": 0.44219062061450254,
      "cost": 1350.0,
      "reward": 240.0,
      "prestige": 0.2,
      "score": 0.029607906715719896
    },
    {
      "agent": "EDU",
      "size": "S",
      "footprint_slots": [
        "s_75"
      ],
      "lp_norm": 0.5261009094162087,
      "cost": 1427.0,
      "reward": 242.0,
      "prestige": 0.2,
      "score": 0.027961214691026998
    },
    {
      "agent": "EDU",
      "size": "S",
      "footprint_slots": [
        "s_3"
      ],
      "lp_norm": 0.4719536113639032,
      "cost": 1372.0,
      "reward": 241.0,
      "prestige": 0.2,
      "score": 0.029504770218868867
    },
    {
      "agent": "EDU",
      "size": "S",
      "footprint_slots": [
        "s_77"
      ],
      "lp_norm": 0.5945726710448597,
      "cost": 1504.0,
      "reward": 245.0,
      "prestige": 0.2,
      "score": 0.027171665523476957
    },
    {
      "agent": "EDU",
      "size": "S",
      "footprint_slots": [
        "s_84"
      ],
      "lp_norm": 0.7695721410258498,
      "cost": 1669.0,
      "reward": 249.0,
      "prestige": 0.2,
      "score": 0.02339814179709422
    },
    {
      "agent": "EDU",
      "size": "S",
      "footprint_slots": [
        "s_17"
      ],
      "lp_norm": 0.6035777474148354,
      "cost": 1504.0,
      "reward": 242.0,
      "prestige": 0.2,
      "score": 0.024600236952048386
    },
    {
      "agent": "EDU",
      "size": "S",
      "footprint_slots": [
        "s_31"
      ],
      "lp_norm": 0.5109444628535986,
      "cost": 1516.0,
      "reward": 286.0,
      "prestige": 0.2,
      "score": 0.06179073392779198
    },
    {
      "agent": "EDU",
      "size": "S",
      "footprint_slots": [
        "s_73"
      ],
      "lp_norm": 0.5043655982750597,
      "cost": 1405.0,
      "reward": 242.0,
      "prestige": 0.2,
      "score": 0.02892149404502089
    },
    {
      "agent": "EDU",
      "size": "S",
      "footprint_slots": [
        "s_18"
      ],
      "lp_norm": 0.6577177790991073,
      "cost": 1559.0,
      "reward": 244.0,
      "prestige": 0.2,
      "score": 0.02391382428134938
    },
    {
      "agent": "EDU",
      "size": "S",
      "footprint_slots": [
        "s_25"
      ],
      "lp_norm": 0.5363674281012148,
      "cost": 1538.0,
      "reward": 286.0,
      "prestige": 0.2,
      "score": 0.0608304545737981
    },
    {
      "agent": "EDU",
      "size": "S",
      "footprint_slots": [
        "s_61"
      ],
      "lp_norm": 0.5668214406893762,
      "cost": 1571.0,
      "reward": 288.0,
      "prestige": 0.2,
      "score": 0.06110432125709298
    },
    {
      "agent": "EDU",
      "size": "S",
      "footprint_slots": [
        "s_26"
      ],
      "lp_norm": 0.6663052170955888,
      "cost": 1670.0,
      "reward": 291.0,
      "prestige": 0.2,
      "score": 0.05935449273554904
    },
    {
      "agent": "EDU",
      "size": "S",
      "footprint_slots": [
        "s_58"
      ],
      "lp_norm": 0.6338241073607348,
      "cost": 1537.0,
      "reward": 242.0,
      "prestige": 0.2,
      "score": 0.023159817921057556
    },
    {
      "agent": "EDU",
      "size": "S",
      "footprint_slots": [
        "s_6"
      ],
      "lp_norm": 0.44929695454942953,
      "cost": 1350.0,
      "reward": 240.0,
      "prestige": 0.2,
      "score": 0.029607906715719896
    },
    {
      "agent": "EDU",
      "size": "S",
      "footprint_slots": [
        "s_38"
      ],
      "lp_norm": 0.7501554859764836,
      "cost": 1758.0,
      "reward": 293.0,
      "prestige": 0.2,
      "score": 0.057227661033859206
    },
    {
      "agent": "EDU",
      "size": "S",
      "footprint_slots": [
        "s_76"
      ],
      "lp_norm": 0.5559463757313021,
      "cost": 1460.0,
      "reward": 243.0,
      "prestige": 0.2,
      "score": 0.02737793851717902
    },
    {
      "agent": "EDU",
      "size": "S",
      "footprint_slots": [
        "s_55"
      ],
      "lp_norm": 0.7922478512883318,
      "cost": 1791.0,
      "reward": 294.0,
      "prestige": 0.2,
      "score": 0.056644384860011235
    },
    {
      "agent": "EDU",
      "size": "M",
      "footprint_slots": [
        "s_11"
      ],
      "lp_norm": 0.6356598004044915,
      "cost": 2137.0,
      "reward": 454.0,
      "prestige": 0.6,
      "score": 0.4036846667082372
    },
    {
      "agent": "EDU",
      "size": "M",
      "footprint_slots": [
        "s_64"
      ],
      "lp_norm": 0.6022468757335105,
      "cost": 2104.0,
      "reward": 454.0,
      "prestige": 0.6,
      "score": 0.405125085739228
    },
    {
      "agent": "EDU",
      "size": "M",
      "footprint_slots": [
        "s_0"
      ],
      "lp_norm": 0.3756127885848022,
      "cost": 1784.0,
      "reward": 398.0,
      "prestige": 0.6,
      "score": 0.37109278543368457
    },
    {
      "agent": "EDU",
      "size": "M",
      "footprint_slots": [
        "s_37"
      ],
      "lp_norm": 0.5730137609877954,
      "cost": 2082.0,
      "reward": 451.0,
      "prestige": 0.6,
      "score": 0.40351393652179335
    },
    {
      "agent": "EDU",
      "size": "M",
      "footprint_slots": [
        "s_4"
      ],
      "lp_norm": 0.3610941999307371,
      "cost": 1762.0,
      "reward": 398.0,
      "prestige": 0.6,
      "score": 0.37205306478767847
    },
    {
      "agent": "EDU",
      "size": "M",
      "footprint_slots": [
        "s_80"
      ],
      "lp_norm": 0.6563306527526704,
      "cost": 2059.0,
      "reward": 413.0,
      "prestige": 0.6,
      "score": 0.37194643636590385
    },
    {
      "agent": "EDU",
      "size": "M",
      "footprint_slots": [
        "s_16"
      ],
      "lp_norm": 0.4452131332452116,
      "cost": 1850.0,
      "reward": 400.0,
      "prestige": 0.6,
      "score": 0.3699262330859886
    },
    {
      "agent": "EDU",
      "size": "M",
      "footprint_slots": [
        "s_12"
      ],
      "lp_norm": 0.536310686040433,
      "cost": 2038.0,
      "reward": 448.0,
      "prestige": 0.6,
      "score": 0.40286306665835253
    },
    {
      "agent": "EDU",
      "size": "M",
      "footprint_slots": [
        "s_14"
      ],
      "lp_norm": 0.5145651173741638,
      "cost": 2016.0,
      "reward": 448.0,
      "prestige": 0.6,
      "score": 0.40382334601234643
    },
    {
      "agent": "EDU",
      "size": "M",
      "footprint_slots": [
        "s_28"
      ],
      "lp_norm": 0.6212639227037201,
      "cost": 2126.0,
      "reward": 454.0,
      "prestige": 0.6,
      "score": 0.40416480638523417
    },
    {
      "agent": "EDU",
      "size": "M",
      "footprint_slots": [
        "s_19"
      ],
      "lp_norm": 0.4235472918721448,
      "cost": 1828.0,
      "reward": 399.0,
      "prestige": 0.6,
      "score": 0.37002936958283966
    },
    {
      "agent": "EDU",
      "size": "M",
      "footprint_slots": [
        "s_79"
      ],
      "lp_norm": 0.5973426126761566,
      "cost": 2004.0,
      "reward": 409.0,
      "prestige": 0.6,
      "score": 0.37091856332231715
    },
    {
      "agent": "EDU",
      "size": "M",
      "footprint_slots": [
        "s_24"
      ],
      "lp_norm": 0.5205655042901448,
      "cost": 1927.0,
      "reward": 405.0,
      "prestige": 0.6,
      "score": 0.3708509696327243
    },
    {
      "agent": "EDU",
      "size": "M",
      "footprint_slots": [
        "s_8"
      ],
      "lp_norm": 0.40117801727205205,
      "cost": 1806.0,
      "reward": 401.0,
      "prestige": 0.6,
      "score": 0.37270393465111923
    },
    {
      "agent": "EDU",
      "size": "M",
      "footprint_slots": [
        "s_20"
      ],
      "lp_norm": 0.5253224084807169,
      "cost": 1927.0,
      "reward": 404.0,
      "prestige": 0.6,
      "score": 0.36999382677558146
    },
    {
      "agent": "EDU",
      "size": "M",
      "footprint_slots": [
        "s_82"
      ],
      "lp_norm": 0.6833946118411781,
      "cost": 2092.0,
      "reward": 412.0,
      "prestige": 0.6,
      "score": 0.3696488744777701
    },
    {
      "agent": "EDU",
      "size": "M",
      "footprint_slots": [
        "s_29"
      ],
      "lp_norm": 0.5607234170649145,
      "cost": 2060.0,
      "reward": 451.0,
      "prestige": 0.6,
      "score": 0.40447421587578725
    },
    {
      "agent": "EDU",
      "size": "M",
      "footprint_slots": [
        "s_30"
      ],
      "lp_norm": 0.618251079311038,
      "cost": 2126.0,
      "reward": 454.0,
      "prestige": 0.6,
      "score": 0.40416480638523417
    },
    {
      "agent": "EDU",
      "size": "M",
      "footprint_slots": [
        "s_10"
      ],
      "lp_norm": 0.5355614348129698,
      "cost": 2038.0,
      "reward": 448.0,
      "prestige": 0.6,
      "score": 0.40286306665835253
    },
    {
      "agent": "EDU",
      "size": "M",
      "footprint_slots": [
        "s_1"
      ],
      "lp_norm": 0.43284247391179026,
      "cost": 1839.0,
      "reward": 401.0,
      "prestige": 0.6,
      "score": 0.3712635156201284
    },
    {
      "agent": "EDU",
      "size": "M",
      "footprint_slots": [
        "s_7"
      ],
      "lp_norm": 0.34234720347939307,
      "cost": 1751.0,
      "reward": 398.0,
      "prestige": 0.6,
      "score": 0.3725332044646754
    },
    {
      "agent": "EDU",
      "size": "M",
      "footprint_slots": [
        "s_34"
      ],
      "lp_norm": 0.5548988764824909,
      "cost": 2060.0,
      "reward": 450.0,
      "prestige": 0.6,
      "score": 0.40361707301864436
    },
    {
      "agent": "EDU",
      "size": "M",
      "footprint_slots": [
        "s_22"
      ],
      "lp_norm": 0.3946067049739341,
      "cost": 1806.0,
      "reward": 398.0,
      "prestige": 0.6,
      "score": 0.37013250607969067
    },
    {
      "agent": "EDU",
      "size": "M",
      "footprint_slots": [
        "s_15"
      ],
      "lp_norm": 0.5720894196601226,
      "cost": 2071.0,
      "reward": 451.0,
      "prestige": 0.6,
      "score": 0.4039940761987903
    },
    {
      "agent": "EDU",
      "size": "M",
      "footprint_slots": [
        "s_295"
      ],
      "lp_norm": 0.4985645829264926,
      "cost": 2005.0,
      "reward": 447.0,
      "prestige": 0.6,
      "score": 0.40344634283220054
    },
    {
      "agent": "EDU",
      "size": "M",
      "footprint_slots": [
        "s_21"
      ],
      "lp_norm": 0.5658460187630443,
      "cost": 1971.0,
      "reward": 406.0,
      "prestige": 0.6,
      "score": 0.3697875537818794
    },
    {
      "agent": "EDU",
      "size": "M",
      "footprint_slots": [
        "s_71"
      ],
      "lp_norm": 0.49041502310587415,
      "cost": 1894.0,
      "reward": 407.0,
      "prestige": 0.6,
      "score": 0.37400567437800086
    },
    {
      "agent": "EDU",
      "size": "M",
      "footprint_slots": [
        "s_83"
      ],
      "lp_norm": 0.712732871809159,
      "cost": 2114.0,
      "reward": 414.0,
      "prestige": 0.6,
      "score": 0.37040288083806194
    },
    {
      "agent": "EDU",
      "size": "M",
      "footprint_slots": [
        "s_2"
      ],
      "lp_norm": 0.5808091889303625,
      "cost": 2082.0,
      "reward": 452.0,
      "prestige": 0.6,
      "score": 0.4043710793789361
    },
    {
      "agent": "EDU",
      "size": "M",
      "footprint_slots": [
        "s_5"
      ],
      "lp_norm": 0.4181704815352727,
      "cost": 1828.0,
      "reward": 401.0,
      "prestige": 0.6,
      "score": 0.37174365529712533
    },
    {
      "agent": "EDU",
      "size": "M",
      "footprint_slots": [
        "s_32"
      ],
      "lp_norm": 0.6618105880510332,
      "cost": 2170.0,
      "reward": 456.0,
      "prestige": 0.6,
      "score": 0.40395853339153204
    },
    {
      "agent": "EDU",
      "size": "M",
      "footprint_slots": [
        "s_13"
      ],
      "lp_norm": 0.5943227411168474,
      "cost": 2093.0,
      "reward": 452.0,
      "prestige": 0.6,
      "score": 0.40389093970193923
    },
    {
      "agent": "EDU",
      "size": "M",
      "footprint_slots": [
        "s_27"
      ],
      "lp_norm": 0.5622849885329231,
      "cost": 2071.0,
      "reward": 450.0,
      "prestige": 0.6,
      "score": 0.4031369333416474
    },
    {
      "agent": "EDU",
      "size": "M",
      "footprint_slots": [
        "s_23"
      ],
      "lp_norm": 0.4684078771266487,
      "cost": 1872.0,
      "reward": 402.0,
      "prestige": 0.6,
      "score": 0.3706802394462805
    },
    {
      "agent": "EDU",
      "size": "M",
      "footprint_slots": [
        "s_9"
      ],
      "lp_norm": 0.44219062061450254,
      "cost": 1850.0,
      "reward": 404.0,
      "prestige": 0.6,
      "score": 0.37335480451456005
    },
    {
      "agent": "EDU",
      "size": "M",
      "footprint_slots": [
        "s_75"
      ],
      "lp_norm": 0.5261009094162087,
      "cost": 1927.0,
      "reward": 407.0,
      "prestige": 0.6,
      "score": 0.37256525534701
    },
    {
      "agent": "EDU",
      "size": "M",
      "footprint_slots": [
        "s_3"
      ],
      "lp_norm": 0.4719536113639032,
      "cost": 1872.0,
      "reward": 404.0,
      "prestige": 0.6,
      "score": 0.3723945251605662
    },
    {
      "agent": "EDU",
      "size": "M",
      "footprint_slots": [
        "s_77"
      ],
      "lp_norm": 0.5945726710448597,
      "cost": 2004.0,
      "reward": 411.0,
      "prestige": 0.6,
      "score": 0.3726328490366028
    },
    {
      "agent": "EDU",
      "size": "M",
      "footprint_slots": [
        "s_84"
      ],
      "lp_norm": 0.7695721410258498,
      "cost": 2169.0,
      "reward": 419.0,
      "prestige": 0.6,
      "score": 0.37228789673879153
    },
    {
      "agent": "EDU",
      "size": "M",
      "footprint_slots": [
        "s_17"
      ],
      "lp_norm": 0.6035777474148354,
      "cost": 2004.0,
      "reward": 407.0,
      "prestige": 0.6,
      "score": 0.36920427760803143
    },
    {
      "agent": "EDU",
      "size": "M",
      "footprint_slots": [
        "s_31"
      ],
      "lp_norm": 0.5109444628535986,
      "cost": 2016.0,
      "reward": 448.0,
      "prestige": 0.6,
      "score": 0.40382334601234643
    },
    {
      "agent": "EDU",
      "size": "M",
      "footprint_slots": [
        "s_73"
      ],
      "lp_norm": 0.5043655982750597,
      "cost": 1905.0,
      "reward": 407.0,
      "prestige": 0.6,
      "score": 0.3735255347010039
    },
    {
      "agent": "EDU",
      "size": "M",
      "footprint_slots": [
        "s_18"
      ],
      "lp_norm": 0.6577177790991073,
      "cost": 2059.0,
      "reward": 410.0,
      "prestige": 0.6,
      "score": 0.36937500779447524
    },
    {
      "agent": "EDU",
      "size": "M",
      "footprint_slots": [
        "s_25"
      ],
      "lp_norm": 0.5363674281012148,
      "cost": 2038.0,
      "reward": 448.0,
      "prestige": 0.6,
      "score": 0.40286306665835253
    },
    {
      "agent": "EDU",
      "size": "M",
      "footprint_slots": [
        "s_61"
      ],
      "lp_norm": 0.5668214406893762,
      "cost": 2071.0,
      "reward": 453.0,
      "prestige": 0.6,
      "score": 0.40570836191307597
    },
    {
      "agent": "EDU",
      "size": "M",
      "footprint_slots": [
        "s_26"
      ],
      "lp_norm": 0.6663052170955888,
      "cost": 2170.0,
      "reward": 456.0,
      "prestige": 0.6,
      "score": 0.40395853339153204
    },
    {
      "agent": "EDU",
      "size": "M",
      "footprint_slots": [
        "s_58"
      ],
      "lp_norm": 0.6338241073607348,
      "cost": 2037.0,
      "reward": 408.0,
      "prestige": 0.6,
      "score": 0.3686210014341834
    },
    {
      "agent": "EDU",
      "size": "M",
      "footprint_slots": [
        "s_6"
      ],
      "lp_norm": 0.44929695454942953,
      "cost": 1850.0,
      "reward": 404.0,
      "prestige": 0.6,
      "score": 0.37335480451456005
    },
    {
      "agent": "EDU",
      "size": "M",
      "footprint_slots": [
        "s_38"
      ],
      "lp_norm": 0.7501554859764836,
      "cost": 2258.0,
      "reward": 461.0,
      "prestige": 0.6,
      "score": 0.40440313026127084
    },
    {
      "agent": "EDU",
      "size": "M",
      "footprint_slots": [
        "s_76"
      ],
      "lp_norm": 0.5559463757313021,
      "cost": 1960.0,
      "reward": 407.0,
      "prestige": 0.6,
      "score": 0.37112483631601917
    },
    {
      "agent": "EDU",
      "size": "M",
      "footprint_slots": [
        "s_55"
      ],
      "lp_norm": 0.7922478512883318,
      "cost": 2291.0,
      "reward": 462.0,
      "prestige": 0.6,
      "score": 0.4038198540874228
    },
    {
      "agent": "EDU",
      "size": "L",
      "footprint_slots": [
        "s_11"
      ],
      "lp_norm": 0.6356598004044915,
      "cost": 2837.0,
      "reward": 672.0,
      "prestige": 1.0,
      "score": 0.7849874664837564
    },
    {
      "agent": "EDU",
      "size": "L",
      "footprint_slots": [
        "s_64"
      ],
      "lp_norm": 0.6022468757335105,
      "cost": 2804.0,
      "reward": 672.0,
      "prestige": 1.0,
      "score": 0.7864278855147472
    },
    {
      "agent": "EDU",
      "size": "L",
      "footprint_slots": [
        "s_0"
      ],
      "lp_norm": 0.3756127885848022,
      "cost": 2484.0,
      "reward": 612.0,
      "prestige": 1.0,
      "score": 0.7489670137806324
    },
    {
      "agent": "EDU",
      "size": "L",
      "footprint_slots": [
        "s_37"
      ],
      "lp_norm": 0.5730137609877954,
      "cost": 2782.0,
      "reward": 668.0,
      "prestige": 1.0,
      "score": 0.7839595934401696
    },
    {
      "agent": "EDU",
      "size": "L",
      "footprint_slots": [
        "s_4"
      ],
      "lp_norm": 0.3610941999307371,
      "cost": 2462.0,
      "reward": 611.0,
      "prestige": 1.0,
      "score": 0.7490701502774832
    },
    {
      "agent": "EDU",
      "size": "L",
      "footprint_slots": [
        "s_80"
      ],
      "lp_norm": 0.6563306527526704,
      "cost": 2759.0,
      "reward": 633.0,
      "prestige": 1.0,
      "score": 0.7549635218557086
    },
    {
      "agent": "EDU",
      "size": "L",
      "footprint_slots": [
        "s_16"
      ],
      "lp_norm": 0.4452131332452116,
      "cost": 2550.0,
      "reward": 614.0,
      "prestige": 1.0,
      "score": 0.7478004614329363
    },
    {
      "agent": "EDU",
      "size": "L",
      "footprint_slots": [
        "s_12"
      ],
      "lp_norm": 0.536310686040433,
      "cost": 2738.0,
      "reward": 663.0,
      "prestige": 1.0,
      "score": 0.7815944378624431
    },
    {
      "agent": "EDU",
      "size": "L",
      "footprint_slots": [
        "s_14"
      ],
      "lp_norm": 0.5145651173741638,
      "cost": 2716.0,
      "reward": 662.0,
      "prestige": 1.0,
      "score": 0.7816975743592941
    },
    {
      "agent": "EDU",
      "size": "L",
      "footprint_slots": [
        "s_28"
      ],
      "lp_norm": 0.6212639227037201,
      "cost": 2826.0,
      "reward": 672.0,
      "prestige": 1.0,
      "score": 0.7854676061607533
    },
    {
      "agent": "EDU",
      "size": "L",
      "footprint_slots": [
        "s_19"
      ],
      "lp_norm": 0.4235472918721448,
      "cost": 2528.0,
      "reward": 612.0,
      "prestige": 1.0,
      "score": 0.7470464550726446
    },
    {
      "agent": "EDU",
      "size": "L",
      "footprint_slots": [
        "s_79"
      ],
      "lp_norm": 0.5973426126761566,
      "cost": 2704.0,
      "reward": 628.0,
      "prestige": 1.0,
      "score": 0.753078505954979
    },
    {
      "agent": "EDU",
      "size": "L",
      "footprint_slots": [
        "s_24"
      ],
      "lp_norm": 0.5205655042901448,
      "cost": 2627.0,
      "reward": 622.0,
      "prestige": 1.0,
      "score": 0.7512966265511006
    },
    {
      "agent": "EDU",
      "size": "L",
      "footprint_slots": [
        "s_8"
      ],
      "lp_norm": 0.40117801727205205,
      "cost": 2506.0,
      "reward": 616.0,
      "prestige": 1.0,
      "score": 0.7514353058552099
    },
    {
      "agent": "EDU",
      "size": "L",
      "footprint_slots": [
        "s_20"
      ],
      "lp_norm": 0.5253224084807169,
      "cost": 2627.0,
      "reward": 620.0,
      "prestige": 1.0,
      "score": 0.7495823408368149
    },
    {
      "agent": "EDU",
      "size": "L",
      "footprint_slots": [
        "s_82"
      ],
      "lp_norm": 0.6833946118411781,
      "cost": 2792.0,
      "reward": 633.0,
      "prestige": 1.0,
      "score": 0.7535231028247178
    },
    {
      "agent": "EDU",
      "size": "L",
      "footprint_slots": [
        "s_29"
      ],
      "lp_norm": 0.5607234170649145,
      "cost": 2760.0,
      "reward": 667.0,
      "prestige": 1.0,
      "score": 0.7840627299370206
    },
    {
      "agent": "EDU",
      "size": "L",
      "footprint_slots": [
        "s_30"
      ],
      "lp_norm": 0.618251079311038,
      "cost": 2826.0,
      "reward": 672.0,
      "prestige": 1.0,
      "score": 0.7854676061607533
    },
    {
      "agent": "EDU",
      "size": "L",
      "footprint_slots": [
        "s_10"
      ],
      "lp_norm": 0.5355614348129698,
      "cost": 2738.0,
      "reward": 663.0,
      "prestige": 1.0,
      "score": 0.7815944378624431
    },
    {
      "agent": "EDU",
      "size": "L",
      "footprint_slots": [
        "s_1"
      ],
      "lp_norm": 0.43284247391179026,
      "cost": 2539.0,
      "reward": 616.0,
      "prestige": 1.0,
      "score": 0.749994886824219
    },
    {
      "agent": "EDU",
      "size": "L",
      "footprint_slots": [
        "s_7"
      ],
      "lp_norm": 0.34234720347939307,
      "cost": 2451.0,
      "reward": 611.0,
      "prestige": 1.0,
      "score": 0.7495502899544803
    },
    {
      "agent": "EDU",
      "size": "L",
      "footprint_slots": [
        "s_34"
      ],
      "lp_norm": 0.5548988764824909,
      "cost": 2760.0,
      "reward": 666.0,
      "prestige": 1.0,
      "score": 0.7832055870798779
    },
    {
      "agent": "EDU",
      "size": "L",
      "footprint_slots": [
        "s_22"
      ],
      "lp_norm": 0.3946067049739341,
      "cost": 2506.0,
      "reward": 612.0,
      "prestige": 1.0,
      "score": 0.7480067344266385
    },
    {
      "agent": "EDU",
      "size": "L",
      "footprint_slots": [
        "s_15"
      ],
      "lp_norm": 0.5720894196601226,
      "cost": 2771.0,
      "reward": 667.0,
      "prestige": 1.0,
      "score": 0.7835825902600237
    },
    {
      "agent": "EDU",
      "size": "L",
      "footprint_slots": [
        "s_295"
      ],
      "lp_norm": 0.4985645829264926,
      "cost": 2705.0,
      "reward": 662.0,
      "prestige": 1.0,
      "score": 0.7821777140362911
    },
    {
      "agent": "EDU",
      "size": "L",
      "footprint_slots": [
        "s_21"
      ],
      "lp_norm": 0.5658460187630443,
      "cost": 2671.0,
      "reward": 624.0,
      "prestige": 1.0,
      "score": 0.7510903535573986
    },
    {
      "agent": "EDU",
      "size": "L",
      "footprint_slots": [
        "s_71"
      ],
      "lp_norm": 0.49041502310587415,
      "cost": 2594.0,
      "reward": 626.0,
      "prestige": 1.0,
      "score": 0.7561656170106629
    },
    {
      "agent": "EDU",
      "size": "L",
      "footprint_slots": [
        "s_83"
      ],
      "lp_norm": 0.712732871809159,
      "cost": 2814.0,
      "reward": 637.0,
      "prestige": 1.0,
      "score": 0.7559913948992955
    },
    {
      "agent": "EDU",
      "size": "L",
      "footprint_slots": [
        "s_2"
      ],
      "lp_norm": 0.5808091889303625,
      "cost": 2782.0,
      "reward": 669.0,
      "prestige": 1.0,
      "score": 0.7848167362973124
    },
    {
      "agent": "EDU",
      "size": "L",
      "footprint_slots": [
        "s_5"
      ],
      "lp_norm": 0.4181704815352727,
      "cost": 2528.0,
      "reward": 616.0,
      "prestige": 1.0,
      "score": 0.750475026501216
    },
    {
      "agent": "EDU",
      "size": "L",
      "footprint_slots": [
        "s_32"
      ],
      "lp_norm": 0.6618105880510332,
      "cost": 2870.0,
      "reward": 675.0,
      "prestige": 1.0,
      "score": 0.7861184760241939
    },
    {
      "agent": "EDU",
      "size": "L",
      "footprint_slots": [
        "s_13"
      ],
      "lp_norm": 0.5943227411168474,
      "cost": 2793.0,
      "reward": 669.0,
      "prestige": 1.0,
      "score": 0.7843365966203155
    },
    {
      "agent": "EDU",
      "size": "L",
      "footprint_slots": [
        "s_27"
      ],
      "lp_norm": 0.5622849885329231,
      "cost": 2771.0,
      "reward": 666.0,
      "prestige": 1.0,
      "score": 0.782725447402881
    },
    {
      "agent": "EDU",
      "size": "L",
      "footprint_slots": [
        "s_23"
      ],
      "lp_norm": 0.4684078771266487,
      "cost": 2572.0,
      "reward": 617.0,
      "prestige": 1.0,
      "score": 0.7494116106503711
    },
    {
      "agent": "EDU",
      "size": "L",
      "footprint_slots": [
        "s_9"
      ],
      "lp_norm": 0.44219062061450254,
      "cost": 2550.0,
      "reward": 621.0,
      "prestige": 1.0,
      "score": 0.7538004614329363
    },
    {
      "agent": "EDU",
      "size": "L",
      "footprint_slots": [
        "s_75"
      ],
      "lp_norm": 0.5261009094162087,
      "cost": 2627.0,
      "reward": 626.0,
      "prestige": 1.0,
      "score": 0.7547251979796721
    },
    {
      "agent": "EDU",
      "size": "L",
      "footprint_slots": [
        "s_3"
      ],
      "lp_norm": 0.4719536113639032,
      "cost": 2572.0,
      "reward": 620.0,
      "prestige": 1.0,
      "score": 0.7519830392217995
    },
    {
      "agent": "EDU",
      "size": "L",
      "footprint_slots": [
        "s_77"
      ],
      "lp_norm": 0.5945726710448597,
      "cost": 2704.0,
      "reward": 631.0,
      "prestige": 1.0,
      "score": 0.7556499345264077
    },
    {
      "agent": "EDU",
      "size": "L",
      "footprint_slots": [
        "s_84"
      ],
      "lp_norm": 0.7695721410258498,
      "cost": 2869.0,
      "reward": 642.0,
      "prestige": 1.0,
      "score": 0.7578764108000249
    },
    {
      "agent": "EDU",
      "size": "L",
      "footprint_slots": [
        "s_17"
      ],
      "lp_norm": 0.6035777474148354,
      "cost": 2704.0,
      "reward": 624.0,
      "prestige": 1.0,
      "score": 0.7496499345264077
    },
    {
      "agent": "EDU",
      "size": "L",
      "footprint_slots": [
        "s_31"
      ],
      "lp_norm": 0.5109444628535986,
      "cost": 2716.0,
      "reward": 664.0,
      "prestige": 1.0,
      "score": 0.7834118600735799
    },
    {
      "agent": "EDU",
      "size": "L",
      "footprint_slots": [
        "s_73"
      ],
      "lp_norm": 0.5043655982750597,
      "cost": 2605.0,
      "reward": 625.0,
      "prestige": 1.0,
      "score": 0.7548283344765232
    },
    {
      "agent": "EDU",
      "size": "L",
      "footprint_slots": [
        "s_18"
      ],
      "lp_norm": 0.6577177790991073,
      "cost": 2759.0,
      "reward": 629.0,
      "prestige": 1.0,
      "score": 0.7515349504271372
    },
    {
      "agent": "EDU",
      "size": "L",
      "footprint_slots": [
        "s_25"
      ],
      "lp_norm": 0.5363674281012148,
      "cost": 2738.0,
      "reward": 663.0,
      "prestige": 1.0,
      "score": 0.7815944378624431
    },
    {
      "agent": "EDU",
      "size": "L",
      "footprint_slots": [
        "s_61"
      ],
      "lp_norm": 0.5668214406893762,
      "cost": 2771.0,
      "reward": 670.0,
      "prestige": 1.0,
      "score": 0.7861540188314523
    },
    {
      "agent": "EDU",
      "size": "L",
      "footprint_slots": [
        "s_26"
      ],
      "lp_norm": 0.6663052170955888,
      "cost": 2870.0,
      "reward": 675.0,
      "prestige": 1.0,
      "score": 0.7861184760241939
    },
    {
      "agent": "EDU",
      "size": "L",
      "footprint_slots": [
        "s_58"
      ],
      "lp_norm": 0.6338241073607348,
      "cost": 2737.0,
      "reward": 626.0,
      "prestige": 1.0,
      "score": 0.7499238012097026
    },
    {
      "agent": "EDU",
      "size": "L",
      "footprint_slots": [
        "s_6"
      ],
      "lp_norm": 0.44929695454942953,
      "cost": 2550.0,
      "reward": 620.0,
      "prestige": 1.0,
      "score": 0.7529433185757934
    },
    {
      "agent": "EDU",
      "size": "L",
      "footprint_slots": [
        "s_38"
      ],
      "lp_norm": 0.7501554859764836,
      "cost": 2958.0,
      "reward": 681.0,
      "prestige": 1.0,
      "score": 0.7874202157510757
    },
    {
      "agent": "EDU",
      "size": "L",
      "footprint_slots": [
        "s_76"
      ],
      "lp_norm": 0.5559463757313021,
      "cost": 2660.0,
      "reward": 626.0,
      "prestige": 1.0,
      "score": 0.7532847789486812
    },
    {
      "agent": "EDU",
      "size": "L",
      "footprint_slots": [
        "s_55"
      ],
      "lp_norm": 0.7922478512883318,
      "cost": 2991.0,
      "reward": 683.0,
      "prestige": 1.0,
      "score": 0.7876940824343706
    }
  ],
  "active_agent": "EDU"
}