{
  "month": 82,
  "count": 207,
  "actions": [
    {
      "agent": "EDU",
      "size": "S",
      "footprint_slots": [
        "s_1193"
      ],
      "lp_norm": 0.8159023501207139,
      "cost": 1713.0,
      "reward": 246.0,
      "prestige": 0.2,
      "score": -0.006380409823790746
    },
    {
      "agent": "EDU",
      "size": "S",
      "footprint_slots": [
        "s_1031"
      ],
      "lp_norm": 0.6517669724518593,
      "cost": 1559.0,
      "reward": 244.0,
      "prestige": 0.2,
      "score": 0.001449639345080617
    },
    {
      "agent": "EDU",
      "size": "S",
      "footprint_slots": [
        "s_1191"
      ],
      "lp_norm": 0.6547942261109497,
      "cost": 1559.0,
      "reward": 243.0,
      "prestige": 0.2,
      "score": 0.00036790857584984775
    },
    {
      "agent": "EDU",
      "size": "S",
      "footprint_slots": [
        "s_1234"
      ],
      "lp_norm": 0.6774430216435886,
      "cost": 1581.0,
      "reward": 243.0,
      "prestige": 0.2,
      "score": -0.0010597358109119956
    },
    {
      "agent": "EDU",
      "size": "S",
      "footprint_slots": [
        "s_1307"
      ],
      "lp_norm": 0.7555287345590923,
      "cost": 1658.0,
      "reward": 246.0,
      "prestige": 0.2,
      "score": -0.002811298856886138
    },
    {
      "agent": "EDU",
      "size": "S",
      "footprint_slots": [
        "s_1331"
      ],
      "lp_norm": 0.6946271647150053,
      "cost": 1603.0,
      "reward": 245.0,
      "prestige": 0.2,
      "score": -0.0003239186592122996
    },
    {
      "agent": "EDU",
      "size": "S",
      "footprint_slots": [
        "s_1056"
      ],
      "lp_norm": 0.7264550306304726,
      "cost": 1625.0,
      "reward": 245.0,
      "prestige": 0.2,
      "score": -0.0017515630459741427
    },
    {
      "agent": "EDU",
      "size": "S",
      "footprint_slots": [
        "s_1403"
      ],
      "lp_norm": 0.7043997187030165,
      "cost": 1603.0,
      "reward": 245.0,
      "prestige": 0.2,
      "score": -0.0003239186592122996
    },
    {
      "agent": "EDU",
      "size": "S",
      "footprint_slots": [
        "s_1327"
      ],
      "lp_norm": 0.8402877350859839,
      "cost": 1746.0,
      "reward": 248.0,
      "prestige": 0.2,
      "score": -0.0063584148654719725
    },
    {
      "agent": "EDU",
      "size": "S",
      "footprint_slots": [
        "s_1042"
      ],
      "lp_norm": 0.6697545474172746,
      "cost": 1570.0,
      "reward": 243.0,
      "prestige": 0.2,
      "score": -0.0003459136175310738
    },
    {
      "agent": "EDU",
      "size": "S",
      "footprint_slots": [
        "s_1213"
      ],
      "lp_norm": 0.855875096300516,
      "cost": 1757.0,
      "reward": 248.0,
      "prestige": 0.2,
      "score": -0.0070722370588528925
    },
    {
      "agent": "EDU",
      "size": "S",
      "footprint_slots": [
        "s_1399"
      ],
      "lp_norm": 0.6988822294234964,
      "cost": 1603.0,
      "reward": 244.0,
      "prestige": 0.2,
      "score": -0.001405649428443069
    },
    {
      "agent": "EDU",
      "size": "S",
      "footprint_slots": [
        "s_1185"
      ],
      "lp_norm": 0.811107934011535,
      "cost": 1713.0,
      "reward": 246.0,
      "prestige": 0.2,
      "score": -0.006380409823790746
    },
    {
      "agent": "EDU",
      "size": "S",
      "footprint_slots": [
        "s_1374"
      ],
      "lp_norm": 0.7894735595301646,
      "cost": 1691.0,
      "reward": 247.0,
      "prestige": 0.2,
      "score": -0.0038710346677981325
    },
    {
      "agent": "EDU",
      "size": "S",
      "footprint_slots": [
        "s_1003"
      ],
      "lp_norm": 0.7947917810413252,
      "cost": 1702.0,
      "reward": 247.0,
      "prestige": 0.2,
      "score": -0.004584856861179054
    },
    {
      "agent": "EDU",
      "size": "S",
      "footprint_slots": [
        "s_1349"
      ],
      "lp_norm": 0.7367696887553298,
      "cost": 1636.0,
      "reward": 246.0,
      "prestige": 0.2,
      "score": -0.0013836544701242952
    },
    {
      "agent": "EDU",
      "size": "S",
      "footprint_slots": [
        "s_955"
      ],
      "lp_norm": 0.7652887852882968,
      "cost": 1669.0,
      "reward": 246.0,
      "prestige": 0.2,
      "score": -0.0035251210502670587
    },
    {
      "agent": "EDU",
      "size": "S",
      "footprint_slots": [
        "s_1012"
      ],
      "lp_norm": 0.7544534402824742,
      "cost": 1658.0,
      "reward": 245.0,
      "prestige": 0.2,
      "score": -0.003893029626116907
    },
    {
      "agent": "EDU",
      "size": "S",
      "footprint_slots": [
        "s_1324"
      ],
      "lp_norm": 0.8287564432704952,
      "cost": 1735.0,
      "reward": 248.0,
      "prestige": 0.2,
      "score": -0.005644592672091051
    },
    {
      "agent": "EDU",
      "size": "S",
      "footprint_slots": [
        "s_1352"
      ],
      "lp_norm": 0.7975882263094929,
      "cost": 1702.0,
      "reward": 246.0,
      "prestige": 0.2,
      "score": -0.005666587630409824
    },
    {
      "agent": "EDU",
      "size": "S",
      "footprint_slots": [
        "s_1210"
      ],
      "lp_norm": 0.80985577176689,
      "cost": 1713.0,
      "reward": 247.0,
      "prestige": 0.2,
      "score": -0.005298679054559976
    },
    {
      "agent": "EDU",
      "size": "S",
      "footprint_slots": [
        "s_1160"
      ],
      "lp_norm": 0.8554594704995576,
      "cost": 1757.0,
      "reward": 248.0,
      "prestige": 0.2,
      "score": -0.0070722370588528925
    },
    {
      "agent": "EDU",
      "size": "S",
      "footprint_slots": [
        "s_1220"
      ],
      "lp_norm": 0.7837392543078846,
      "cost": 1691.0,
      "reward": 246.0,
      "prestige": 0.2,
      "score": -0.004952765437028902
    },
    {
      "agent": "EDU",
      "size": "S",
      "footprint_slots": [
        "s_1390"
      ],
      "lp_norm": 0.7297415440274295,
      "cost": 1636.0,
      "reward": 244.0,
      "prestige": 0.2,
      "score": -0.0035471160085858338
    },
    {
      "agent": "EDU",
      "size": "S",
      "footprint_slots": [
        "s_1389"
      ],
      "lp_norm": 0.6794700727934657,
      "cost": 1581.0,
      "reward": 244.0,
      "prestige": 0.2,
      "score": 2.1994958318773735e-05
    },
    {
      "agent": "EDU",
      "size": "S",
      "footprint_slots": [
        "s_1144"
      ],
      "lp_norm": 0.8282062525655072,
      "cost": 1735.0,
      "reward": 248.0,
      "prestige": 0.2,
      "score": -0.005644592672091051
    },
    {
      "agent": "EDU",
      "size": "S",
      "footprint_slots": [
        "s_1345"
      ],
      "lp_norm": 0.792035721926859,
      "cost": 1691.0,
      "reward": 247.0,
      "prestige": 0.2,
      "score": -0.0038710346677981325
    },
    {
      "agent": "EDU",
      "size": "S",
      "footprint_slots": [
        "s_1381"
      ],
      "lp_norm": 0.7722180175970745,
      "cost": 1669.0,
      "reward": 246.0,
      "prestige": 0.2,
      "score": -0.0035251210502670587
    },
    {
      "agent": "EDU",
      "size": "S",
      "footprint_slots": [
        "s_1037"
      ],
      "lp_norm": 0.6766832318602001,
      "cost": 1581.0,
      "reward": 243.0,
      "prestige": 0.2,
      "score": -0.0010597358109119956
    },
    {
      "agent": "EDU",
      "size": "S",
      "footprint_slots": [
        "s_1155"
      ],
      "lp_norm": 0.8691147621599544,
      "cost": 1768.0,
      "reward": 249.0,
      "prestige": 0.2,
      "score": -0.006704328483003045
    },
    {
      "agent": "EDU",
      "size": "S",
      "footprint_slots": [
        "s_1029"
      ],
      "lp_norm": 0.7155966118861543,
      "cost": 1614.0,
      "reward": 245.0,
      "prestige": 0.2,
      "score": -0.0010377408525932218
    },
    {
      "agent": "EDU",
      "size": "S",
      "footprint_slots": [
        "s_1032"
      ],
      "lp_norm": 0.6757593131795081,
      "cost": 1581.0,
      "reward": 244.0,
      "prestige": 0.2,
      "score": 2.1994958318773735e-05
    },
    {
      "agent": "EDU",
      "size": "S",
      "footprint_slots": [
        "s_1292"
      ],
      "lp_norm": 0.855412260381711,
      "cost": 1757.0,
      "reward": 248.0,
      "prestige": 0.2,
      "score": -0.0070722370588528925
    },
    {
      "agent": "EDU",
      "size": "S",
      "footprint_slots": [
        "s_1147"
      ],
      "lp_norm": 0.8565415811451867,
      "cost": 1757.0,
      "reward": 248.0,
      "prestige": 0.2,
      "score": -0.0070722370588528925
    },
    {
      "agent": "EDU",
      "size": "S",
      "footprint_slots": [
        "s_1541"
      ],
      "lp_norm": 0.6783115493273695,
      "cost": 1581.0,
      "reward": 244.0,
      "prestige": 0.2,
      "score": 2.1994958318773735e-05
    },
    {
      "agent": "EDU",
      "size": "S",
      "footprint_slots": [
        "s_1355"
      ],
      "lp_norm": 0.7203387332080297,
      "cost": 1625.0,
      "reward": 244.0,
      "prestige": 0.2,
      "score": -0.002833293815204912
    },
    {
      "agent": "EDU",
      "size": "S",
      "footprint_slots": [
        "s_1181"
      ],
      "lp_norm": 0.8063134278052271,
      "cost": 1713.0,
      "reward": 247.0,
      "prestige": 0.2,
      "score": -0.005298679054559976
    },
    {
      "agent": "EDU",
      "size": "S",
      "footprint_slots": [
        "s_1175"
      ],
      "lp_norm": 0.886548093431764,
      "cost": 1790.0,
      "reward": 249.0,
      "prestige": 0.2,
      "score": -0.008131972869764886
    },
    {
      "agent": "EDU",
      "size": "S",
      "footprint_slots": [
        "s_1383"
      ],
      "lp_norm": 0.6769311713908425,
      "cost": 1581.0,
      "reward": 243.0,
      "prestige": 0.2,
      "score": -0.0010597358109119956
    },
    {
      "agent": "EDU",
      "size": "S",
      "footprint_slots": [
        "s_1126"
      ],
      "lp_norm": 0.8795879730474611,
      "cost": 1779.0,
      "reward": 249.0,
      "prestige": 0.2,
      "score": -0.007418150676383969
    },
    {
      "agent": "EDU",
      "size": "S",
      "footprint_slots": [
        "s_1054"
      ],
      "lp_norm": 0.7832115888686615,
      "cost": 1680.0,
      "reward": 247.0,
      "prestige": 0.2,
      "score": -0.0031572124744172125
    },
    {
      "agent": "EDU",
      "size": "S",
      "footprint_slots": [
        "s_1214"
      ],
      "lp_norm": 0.7873641966486756,
      "cost": 1691.0,
      "reward": 246.0,
      "prestige": 0.2,
      "score": -0.004952765437028902
    },
    {
      "agent": "EDU",
      "size": "S",
      "footprint_slots": [
        "s_1488"
      ],
      "lp_norm": 0.656011598378926,
      "cost": 1559.0,
      "reward": 244.0,
      "prestige": 0.2,
      "score": 0.001449639345080617
    },
    {
      "agent": "EDU",
      "size": "S",
      "footprint_slots": [
        "s_1203"
      ],
      "lp_norm": 0.6590590756676202,
      "cost": 1559.0,
      "reward": 243.0,
      "prestige": 0.2,
      "score": 0.00036790857584984775
    },
    {
      "agent": "EDU",
      "size": "S",
      "footprint_slots": [
        "s_1186"
      ],
      "lp_norm": 0.8263348287063033,
      "cost": 1724.0,
      "reward": 248.0,
      "prestige": 0.2,
      "score": -0.004930770478710129
    },
    {
      "agent": "EDU",
      "size": "S",
      "footprint_slots": [
        "s_1379"
      ],
      "lp_norm": 0.7562315142118713,
      "cost": 1658.0,
      "reward": 246.0,
      "prestige": 0.2,
      "score": -0.002811298856886138
    },
    {
      "agent": "EDU",
      "size": "S",
      "footprint_slots": [
        "s_1405"
      ],
      "lp_norm": 0.6639062995339491,
      "cost": 1570.0,
      "reward": 243.0,
      "prestige": 0.2,
      "score": -0.0003459136175310738
    },
    {
      "agent": "EDU",
      "size": "S",
      "footprint_slots": [
        "s_1223"
      ],
      "lp_norm": 0.8285127165378043,
      "cost": 1735.0,
      "reward": 247.0,
      "prestige": 0.2,
      "score": -0.0067263234413218196
    },
    {
      "agent": "EDU",
      "size": "S",
      "footprint_slots": [
        "s_1050"
      ],
      "lp_norm": 0.7489873621946224,
      "cost": 1647.0,
      "reward": 246.0,
      "prestige": 0.2,
      "score": -0.002097476663505217
    },
    {
      "agent": "EDU",
      "size": "S",
      "footprint_slots": [
        "s_1217"
      ],
      "lp_norm": 0.8490228007501379,
      "cost": 1746.0,
      "reward": 248.0,
      "prestige": 0.2,
      "score": -0.0063584148654719725
    },
    {
      "agent": "EDU",
      "size": "S",
      "footprint_slots": [
        "s_1502"
      ],
      "lp_norm": 0.6473418205683608,
      "cost": 1548.0,
      "reward": 245.0,
      "prestige": 0.2,
      "score": 0.003245192307692308
    },
    {
      "agent": "EDU",
      "size": "S",
      "footprint_slots": [
        "s_1216"
      ],
      "lp_norm": 0.8477008676787294,
      "cost": 1746.0,
      "reward": 247.0,
      "prestige": 0.2,
      "score": -0.007440145634702741
    },
    {
      "agent": "EDU",
      "size": "S",
      "footprint_slots": [
        "s_1182"
      ],
      "lp_norm": 0.7594183759256643,
      "cost": 1658.0,
      "reward": 245.0,
      "prestige": 0.2,
      "score": -0.003893029626116907
    },
    {
      "agent": "EDU",
      "size": "S",
      "footprint_slots": [
        "s_1027"
      ],
      "lp_norm": 0.735125810439303,
      "cost": 1636.0,
      "reward": 246.0,
      "prestige": 0.2,
      "score": -0.0013836544701242952
    },
    {
      "agent": "EDU",
      "size": "S",
      "footprint_slots": [
        "s_1353"
      ],
      "lp_norm": 0.678149627761237,
      "cost": 1581.0,
      "reward": 243.0,
      "prestige": 0.2,
      "score": -0.0010597358109119956
    },
    {
      "agent": "EDU",
      "size": "S",
      "footprint_slots": [
        "s_1404"
      ],
      "lp_norm": 0.6925897232340035,
      "cost": 1592.0,
      "reward": 245.0,
      "prestige": 0.2,
      "score": 0.0003899035341686217
    },
    {
      "agent": "EDU",
      "size": "S",
      "footprint_slots": [
        "s_1357"
      ],
      "lp_norm": 0.7780253740444703,
      "cost": 1680.0,
      "reward": 247.0,
      "prestige": 0.2,
      "score": -0.0031572124744172125
    },
    {
      "agent": "EDU",
      "size": "S",
      "footprint_slots": [
        "s_1360"
      ],
      "lp_norm": 0.7202601619239161,
      "cost": 1625.0,
      "reward": 245.0,
      "prestige": 0.2,
      "score": -0.0017515630459741427
    },
    {
      "agent": "EDU",
      "size": "S",
      "footprint_slots": [
        "s_1362"
      ],
      "lp_norm": 0.8425577470915846,
      "cost": 1746.0,
      "reward": 248.0,
      "prestige": 0.2,
      "score": -0.0063584148654719725
    },
    {
      "agent": "EDU",
      "size": "S",
      "footprint_slots": [
        "s_1005"
      ],
      "lp_norm": 0.67899952675558,
      "cost": 1581.0,
      "reward": 244.0,
      "prestige": 0.2,
      "score": 2.1994958318773735e-05
    },
    {
      "agent": "EDU",
      "size": "S",
      "footprint_slots": [
        "s_1358"
      ],
      "lp_norm": 0.8346858005218297,
      "cost": 1735.0,
      "reward": 248.0,
      "prestige": 0.2,
      "score": -0.005644592672091051
    },
    {
      "agent": "EDU",
      "size": "S",
      "footprint_slots": [
        "s_1411"
      ],
      "lp_norm": 0.6724213937172416,
      "cost": 1581.0,
      "reward": 243.0,
      "prestige": 0.2,
      "score": -0.0010597358109119956
    },
    {
      "agent": "EDU",
      "size": "S",
      "footprint_slots": [
        "s_1368"
      ],
      "lp_norm": 0.7374011059236654,
      "cost": 1636.0,
      "reward": 245.0,
      "prestige": 0.2,
      "score": -0.0024653852393550645
    },
    {
      "agent": "EDU",
      "size": "S",
      "footprint_slots": [
        "s_1384"
      ],
      "lp_norm": 0.7045934466136099,
      "cost": 1603.0,
      "reward": 244.0,
      "prestige": 0.2,
      "score": -0.001405649428443069
    },
    {
      "agent": "EDU",
      "size": "S",
      "footprint_slots": [
        "s_992"
      ],
      "lp_norm": 0.7111088907632295,
      "cost": 1614.0,
      "reward": 245.0,
      "prestige": 0.2,
      "score": -0.0010377408525932218
    },
    {
      "agent": "EDU",
      "size": "S",
      "footprint_slots": [
        "s_1334"
      ],
      "lp_norm": 0.7368768972170006,
      "cost": 1636.0,
      "reward": 246.0,
      "prestige": 0.2,
      "score": -0.0013836544701242952
    },
    {
      "agent": "EDU",
      "size": "S",
      "footprint_slots": [
        "s_1190"
      ],
      "lp_norm": 0.6546948728260229,
      "cost": 1559.0,
      "reward": 242.0,
      "prestige": 0.2,
      "score": -0.0007138221933809215
    },
    {
      "agent": "EDU",
      "size": "S",
      "footprint_slots": [
        "s_1332"
      ],
      "lp_norm": 0.8185395828933737,
      "cost": 1724.0,
      "reward": 248.0,
      "prestige": 0.2,
      "score": -0.004930770478710129
    },
    {
      "agent": "EDU",
      "size": "S",
      "footprint_slots": [
        "s_1195"
      ],
      "lp_norm": 0.7847619642065327,
      "cost": 1691.0,
      "reward": 247.0,
      "prestige": 0.2,
      "score": -0.0038710346677981325
    },
    {
      "agent": "EDU",
      "size": "M",
      "footprint_slots": [
        "s_1193"
      ],
      "lp_norm": 0.8159023501207139,
      "cost": 2213.0,
      "reward": 415.0,
      "prestige": 0.6,
      "score": 0.36898562684071284
    },
    {
      "agent": "EDU",
      "size": "M",
      "footprint_slots": [
        "s_1031"
      ],
      "lp_norm": 0.6517669724518593,
      "cost": 2059.0,
      "reward": 410.0,
      "prestige": 0.6,
      "score": 0.3735704837018919
    },
    {
      "agent": "EDU",
      "size": "M",
      "footprint_slots": [
        "s_1191"
      ],
      "lp_norm": 0.6547942261109497,
      "cost": 2059.0,
      "reward": 409.0,
      "prestige": 0.6,
      "score": 0.3724887529326611
    },
    {
      "agent": "EDU",
      "size": "M",
      "footprint_slots": [
        "s_1234"
      ],
      "lp_norm": 0.6774430216435886,
      "cost": 2081.0,
      "reward": 409.0,
      "prestige": 0.6,
      "score": 0.37106110854589924
    },
    {
      "agent": "EDU",
      "size": "M",
      "footprint_slots": [
        "s_1307"
      ],
      "lp_norm": 0.7555287345590923,
      "cost": 2158.0,
      "reward": 414.0,
      "prestige": 0.6,
      "score": 0.37147300703838665
    },
    {
      "agent": "EDU",
      "size": "M",
      "footprint_slots": [
        "s_1331"
      ],
      "lp_norm": 0.6946271647150053,
      "cost": 2103.0,
      "reward": 412.0,
      "prestige": 0.6,
      "score": 0.3728786564668297
    },
    {
      "agent": "EDU",
      "size": "M",
      "footprint_slots": [
        "s_1056"
      ],
      "lp_norm": 0.7264550306304726,
      "cost": 2125.0,
      "reward": 413.0,
      "prestige": 0.6,
      "score": 0.3725327428492986
    },
    {
      "agent": "EDU",
      "size": "M",
      "footprint_slots": [
        "s_1403"
      ],
      "lp_norm": 0.7043997187030165,
      "cost": 2103.0,
      "reward": 411.0,
      "prestige": 0.6,
      "score": 0.371796925697599
    },
    {
      "agent": "EDU",
      "size": "M",
      "footprint_slots": [
        "s_1327"
      ],
      "lp_norm": 0.8402877350859839,
      "cost": 2246.0,
      "reward": 418.0,
      "prestige": 0.6,
      "score": 0.37008935256826236
    },
    {
      "agent": "EDU",
      "size": "M",
      "footprint_slots": [
        "s_1042"
      ],
      "lp_norm": 0.6697545474172746,
      "cost": 2070.0,
      "reward": 409.0,
      "prestige": 0.6,
      "score": 0.37177493073928014
    },
    {
      "agent": "EDU",
      "size": "M",
      "footprint_slots": [
        "s_1213"
      ],
      "lp_norm": 0.855875096300516,
      "cost": 2257.0,
      "reward": 418.0,
      "prestige": 0.6,
      "score": 0.3693755303748814
    },
    {
      "agent": "EDU",
      "size": "M",
      "footprint_slots": [
        "s_1399"
      ],
      "lp_norm": 0.6988822294234964,
      "cost": 2103.0,
      "reward": 409.0,
      "prestige": 0.6,
      "score": 0.3696334641591374
    },
    {
      "agent": "EDU",
      "size": "M",
      "footprint_slots": [
        "s_1185"
      ],
      "lp_norm": 0.811107934011535,
      "cost": 2213.0,
      "reward": 415.0,
      "prestige": 0.6,
      "score": 0.36898562684071284
    },
    {
      "agent": "EDU",
      "size": "M",
      "footprint_slots": [
        "s_1374"
      ],
      "lp_norm": 0.7894735595301646,
      "cost": 2191.0,
      "reward": 415.0,
      "prestige": 0.6,
      "score": 0.3704132712274747
    },
    {
      "agent": "EDU",
      "size": "M",
      "footprint_slots": [
        "s_1003"
      ],
      "lp_norm": 0.7947917810413252,
      "cost": 2202.0,
      "reward": 415.0,
      "prestige": 0.6,
      "score": 0.36969944903409374
    },
    {
      "agent": "EDU",
      "size": "M",
      "footprint_slots": [
        "s_1349"
      ],
      "lp_norm": 0.7367696887553298,
      "cost": 2136.0,
      "reward": 413.0,
      "prestige": 0.6,
      "score": 0.3718189206559177
    },
    {
      "agent": "EDU",
      "size": "M",
      "footprint_slots": [
        "s_955"
      ],
      "lp_norm": 0.7652887852882968,
      "cost": 2169.0,
      "reward": 415.0,
      "prestige": 0.6,
      "score": 0.3718409156142365
    },
    {
      "agent": "EDU",
      "size": "M",
      "footprint_slots": [
        "s_1012"
      ],
      "lp_norm": 0.7544534402824742,
      "cost": 2158.0,
      "reward": 413.0,
      "prestige": 0.6,
      "score": 0.37039127626915586
    },
    {
      "agent": "EDU",
      "size": "M",
      "footprint_slots": [
        "s_1324"
      ],
      "lp_norm": 0.8287564432704952,
      "cost": 2235.0,
      "reward": 418.0,
      "prestige": 0.6,
      "score": 0.37080317476164326
    },
    {
      "agent": "EDU",
      "size": "M",
      "footprint_slots": [
        "s_1352"
      ],
      "lp_norm": 0.7975882263094929,
      "cost": 2202.0,
      "reward": 414.0,
      "prestige": 0.6,
      "score": 0.36861771826486295
    },
    {
      "agent": "EDU",
      "size": "M",
      "footprint_slots": [
        "s_1210"
      ],
      "lp_norm": 0.80985577176689,
      "cost": 2213.0,
      "reward": 416.0,
      "prestige": 0.6,
      "score": 0.3700673576099436
    },
    {
      "agent": "EDU",
      "size": "M",
      "footprint_slots": [
        "s_1160"
      ],
      "lp_norm": 0.8554594704995576,
      "cost": 2257.0,
      "reward": 418.0,
      "prestige": 0.6,
      "score": 0.3693755303748814
    },
    {
      "agent": "EDU",
      "size": "M",
      "footprint_slots": [
        "s_1220"
      ],
      "lp_norm": 0.7837392543078846,
      "cost": 2191.0,
      "reward": 414.0,
      "prestige": 0.6,
      "score": 0.3693315404582439
    },
    {
      "agent": "EDU",
      "size": "M",
      "footprint_slots": [
        "s_1390"
      ],
      "lp_norm": 0.7297415440274295,
      "cost": 2136.0,
      "reward": 412.0,
      "prestige": 0.6,
      "score": 0.37073718988668697
    },
    {
      "agent": "EDU",
      "size": "M",
      "footprint_slots": [
        "s_1389"
      ],
      "lp_norm": 0.6794700727934657,
      "cost": 2081.0,
      "reward": 411.0,
      "prestige": 0.6,
      "score": 0.37322457008436083
    },
    {
      "agent": "EDU",
      "size": "M",
      "footprint_slots": [
        "s_1144"
      ],
      "lp_norm": 0.8282062525655072,
      "cost": 2235.0,
      "reward": 418.0,
      "prestige": 0.6,
      "score": 0.37080317476164326
    },
    {
      "agent": "EDU",
      "size": "M",
      "footprint_slots": [
        "s_1345"
      ],
      "lp_norm": 0.792035721926859,
      "cost": 2191.0,
      "reward": 415.0,
      "prestige": 0.6,
      "score": 0.3704132712274747
    },
    {
      "agent": "EDU",
      "size": "M",
      "footprint_slots": [
        "s_1381"
      ],
      "lp_norm": 0.7722180175970745,
      "cost": 2169.0,
      "reward": 414.0,
      "prestige": 0.6,
      "score": 0.3707591848450057
    },
    {
      "agent": "EDU",
      "size": "M",
      "footprint_slots": [
        "s_1037"
      ],
      "lp_norm": 0.6766832318602001,
      "cost": 2081.0,
      "reward": 410.0,
      "prestige": 0.6,
      "score": 0.37214283931513004
    },
    {
      "agent": "EDU",
      "size": "M",
      "footprint_slots": [
        "s_1155"
      ],
      "lp_norm": 0.8691147621599544,
      "cost": 2268.0,
      "reward": 419.0,
      "prestige": 0.6,
      "score": 0.36974343895073125
    },
    {
      "agent": "EDU",
      "size": "M",
      "footprint_slots": [
        "s_1029"
      ],
      "lp_norm": 0.7155966118861543,
      "cost": 2114.0,
      "reward": 412.0,
      "prestige": 0.6,
      "score": 0.3721648342734488
    },
    {
      "agent": "EDU",
      "size": "M",
      "footprint_slots": [
        "s_1032"
      ],
      "lp_norm": 0.6757593131795081,
      "cost": 2081.0,
      "reward": 411.0,
      "prestige": 0.6,
      "score": 0.37322457008436083
    },
    {
      "agent": "EDU",
      "size": "M",
      "footprint_slots": [
        "s_1292"
      ],
      "lp_norm": 0.855412260381711,
      "cost": 2257.0,
      "reward": 419.0,
      "prestige": 0.6,
      "score": 0.3704572611441122
    },
    {
      "agent": "EDU",
      "size": "M",
      "footprint_slots": [
        "s_1147"
      ],
      "lp_norm": 0.8565415811451867,
      "cost": 2257.0,
      "reward": 419.0,
      "prestige": 0.6,
      "score": 0.3704572611441122
    },
    {
      "agent": "EDU",
      "size": "M",
      "footprint_slots": [
        "s_1541"
      ],
      "lp_norm": 0.6783115493273695,
      "cost": 2081.0,
      "reward": 411.0,
      "prestige": 0.6,
      "score": 0.37322457008436083
    },
    {
      "agent": "EDU",
      "size": "M",
      "footprint_slots": [
        "s_1355"
      ],
      "lp_norm": 0.7203387332080297,
      "cost": 2125.0,
      "reward": 411.0,
      "prestige": 0.6,
      "score": 0.37036928131083713
    },
    {
      "agent": "EDU",
      "size": "M",
      "footprint_slots": [
        "s_1181"
      ],
      "lp_norm": 0.8063134278052271,
      "cost": 2213.0,
      "reward": 416.0,
      "prestige": 0.6,
      "score": 0.3700673576099436
    },
    {
      "agent": "EDU",
      "size": "M",
      "footprint_slots": [
        "s_1175"
      ],
      "lp_norm": 0.886548093431764,
      "cost": 2290.0,
      "reward": 419.0,
      "prestige": 0.6,
      "score": 0.36831579456396946
    },
    {
      "agent": "EDU",
      "size": "M",
      "footprint_slots": [
        "s_1383"
      ],
      "lp_norm": 0.6769311713908425,
      "cost": 2081.0,
      "reward": 409.0,
      "prestige": 0.6,
      "score": 0.37106110854589924
    },
    {
      "agent": "EDU",
      "size": "M",
      "footprint_slots": [
        "s_1126"
      ],
      "lp_norm": 0.8795879730474611,
      "cost": 2279.0,
      "reward": 418.0,
      "prestige": 0.6,
      "score": 0.36794788598811956
    },
    {
      "agent": "EDU",
      "size": "M",
      "footprint_slots": [
        "s_1054"
      ],
      "lp_norm": 0.7832115888686615,
      "cost": 2180.0,
      "reward": 415.0,
      "prestige": 0.6,
      "score": 0.3711270934208556
    },
    {
      "agent": "EDU",
      "size": "M",
      "footprint_slots": [
        "s_1214"
      ],
      "lp_norm": 0.7873641966486756,
      "cost": 2191.0,
      "reward": 413.0,
      "prestige": 0.6,
      "score": 0.3682498096890131
    },
    {
      "agent": "EDU",
      "size": "M",
      "footprint_slots": [
        "s_1488"
      ],
      "lp_norm": 0.656011598378926,
      "cost": 2059.0,
      "reward": 410.0,
      "prestige": 0.6,
      "score": 0.3735704837018919
    },
    {
      "agent": "EDU",
      "size": "M",
      "footprint_slots": [
        "s_1203"
      ],
      "lp_norm": 0.6590590756676202,
      "cost": 2059.0,
      "reward": 408.0,
      "prestige": 0.6,
      "score": 0.37140702216343036
    },
    {
      "agent": "EDU",
      "size": "M",
      "footprint_slots": [
        "s_1186"
      ],
      "lp_norm": 0.8263348287063033,
      "cost": 2224.0,
      "reward": 416.0,
      "prestige": 0.6,
      "score": 0.36935353541656263
    },
    {
      "agent": "EDU",
      "size": "M",
      "footprint_slots": [
        "s_1379"
      ],
      "lp_norm": 0.7562315142118713,
      "cost": 2158.0,
      "reward": 413.0,
      "prestige": 0.6,
      "score": 0.37039127626915586
    },
    {
      "agent": "EDU",
      "size": "M",
      "footprint_slots": [
        "s_1405"
      ],
      "lp_norm": 0.6639062995339491,
      "cost": 2070.0,
      "reward": 409.0,
      "prestige": 0.6,
      "score": 0.37177493073928014
    },
    {
      "agent": "EDU",
      "size": "M",
      "footprint_slots": [
        "s_1223"
      ],
      "lp_norm": 0.8285127165378043,
      "cost": 2235.0,
      "reward": 415.0,
      "prestige": 0.6,
      "score": 0.367557982453951
    },
    {
      "agent": "EDU",
      "size": "M",
      "footprint_slots": [
        "s_1050"
      ],
      "lp_norm": 0.7489873621946224,
      "cost": 2147.0,
      "reward": 413.0,
      "prestige": 0.6,
      "score": 0.37110509846253675
    },
    {
      "agent": "EDU",
      "size": "M",
      "footprint_slots": [
        "s_1217"
      ],
      "lp_norm": 0.8490228007501379,
      "cost": 2246.0,
      "reward": 417.0,
      "prestige": 0.6,
      "score": 0.36900762179903157
    },
    {
      "agent": "EDU",
      "size": "M",
      "footprint_slots": [
        "s_1502"
      ],
      "lp_norm": 0.6473418205683608,
      "cost": 2048.0,
      "reward": 412.0,
      "prestige": 0.6,
      "score": 0.3764477674337343
    },
    {
      "agent": "EDU",
      "size": "M",
      "footprint_slots": [
        "s_1216"
      ],
      "lp_norm": 0.8477008676787294,
      "cost": 2246.0,
      "reward": 416.0,
      "prestige": 0.6,
      "score": 0.3679258910298008
    },
    {
      "agent": "EDU",
      "size": "M",
      "footprint_slots": [
        "s_1182"
      ],
      "lp_norm": 0.7594183759256643,
      "cost": 2158.0,
      "reward": 412.0,
      "prestige": 0.6,
      "score": 0.3693095454999251
    },
    {
      "agent": "EDU",
      "size": "M",
      "footprint_slots": [
        "s_1027"
      ],
      "lp_norm": 0.735125810439303,
      "cost": 2136.0,
      "reward": 413.0,
      "prestige": 0.6,
      "score": 0.3718189206559177
    },
    {
      "agent": "EDU",
      "size": "M",
      "footprint_slots": [
        "s_1353"
      ],
      "lp_norm": 0.678149627761237,
      "cost": 2081.0,
      "reward": 410.0,
      "prestige": 0.6,
      "score": 0.37214283931513004
    },
    {
      "agent": "EDU",
      "size": "M",
      "footprint_slots": [
        "s_1404"
      ],
      "lp_norm": 0.6925897232340035,
      "cost": 2092.0,
      "reward": 411.0,
      "prestige": 0.6,
      "score": 0.37251074789097993
    },
    {
      "agent": "EDU",
      "size": "M",
      "footprint_slots": [
        "s_1357"
      ],
      "lp_norm": 0.7780253740444703,
      "cost": 2180.0,
      "reward": 415.0,
      "prestige": 0.6,
      "score": 0.3711270934208556
    },
    {
      "agent": "EDU",
      "size": "M",
      "footprint_slots": [
        "s_1360"
      ],
      "lp_norm": 0.7202601619239161,
      "cost": 2125.0,
      "reward": 411.0,
      "prestige": 0.6,
      "score": 0.37036928131083713
    },
    {
      "agent": "EDU",
      "size": "M",
      "footprint_slots": [
        "s_1362"
      ],
      "lp_norm": 0.8425577470915846,
      "cost": 2246.0,
      "reward": 417.0,
      "prestige": 0.6,
      "score": 0.36900762179903157
    },
    {
      "agent": "EDU",
      "size": "M",
      "footprint_slots": [
        "s_1005"
      ],
      "lp_norm": 0.67899952675558,
      "cost": 2081.0,
      "reward": 412.0,
      "prestige": 0.6,
      "score": 0.37430630085359157
    },
    {
      "agent": "EDU",
      "size": "M",
      "footprint_slots": [
        "s_1358"
      ],
      "lp_norm": 0.8346858005218297,
      "cost": 2235.0,
      "reward": 417.0,
      "prestige": 0.6,
      "score": 0.36972144399241247
    },
    {
      "agent": "EDU",
      "size": "M",
      "footprint_slots": [
        "s_1411"
      ],
      "lp_norm": 0.6724213937172416,
      "cost": 2081.0,
      "reward": 408.0,
      "prestige": 0.6,
      "score": 0.3699793777766685
    },
    {
      "agent": "EDU",
      "size": "M",
      "footprint_slots": [
        "s_1368"
      ],
      "lp_norm": 0.7374011059236654,
      "cost": 2136.0,
      "reward": 411.0,
      "prestige": 0.6,
      "score": 0.36965545911745623
    },
    {
      "agent": "EDU",
      "size": "M",
      "footprint_slots": [
        "s_1384"
      ],
      "lp_norm": 0.7045934466136099,
      "cost": 2103.0,
      "reward": 411.0,
      "prestige": 0.6,
      "score": 0.371796925697599
    },
    {
      "agent": "EDU",
      "size": "M",
      "footprint_slots": [
        "s_992"
      ],
      "lp_norm": 0.7111088907632295,
      "cost": 2114.0,
      "reward": 413.0,
      "prestige": 0.6,
      "score": 0.37324656504267956
    },
    {
      "agent": "EDU",
      "size": "M",
      "footprint_slots": [
        "s_1334"
      ],
      "lp_norm": 0.7368768972170006,
      "cost": 2136.0,
      "reward": 414.0,
      "prestige": 0.6,
      "score": 0.3729006514251485
    },
    {
      "agent": "EDU",
      "size": "M",
      "footprint_slots": [
        "s_1190"
      ],
      "lp_norm": 0.6546948728260229,
      "cost": 2059.0,
      "reward": 407.0,
      "prestige": 0.6,
      "score": 0.37032529139419956
    },
    {
      "agent": "EDU",
      "size": "M",
      "footprint_slots": [
        "s_1332"
      ],
      "lp_norm": 0.8185395828933737,
      "cost": 2224.0,
      "reward": 417.0,
      "prestige": 0.6,
      "score": 0.37043526618579337
    },
    {
      "agent": "EDU",
      "size": "M",
      "footprint_slots": [
        "s_1195"
      ],
      "lp_norm": 0.7847619642065327,
      "cost": 2191.0,
      "reward": 415.0,
      "prestige": 0.6,
      "score": 0.3704132712274747
    },
    {
      "agent": "EDU",
      "size": "L",
      "footprint_slots": [
        "s_1193"
      ],
      "lp_norm": 0.8159023501207139,
      "cost": 2913.0,
      "reward": 638.0,
      "prestige": 1.0,
      "score": 0.7897865397094793
    },
    {
      "agent": "EDU",
      "size": "L",
      "footprint_slots": [
        "s_1031"
      ],
      "lp_norm": 0.6517669724518593,
      "cost": 2759.0,
      "reward": 629.0,
      "prestige": 1.0,
      "score": 0.7900444734937354
    },
    {
      "agent": "EDU",
      "size": "L",
      "footprint_slots": [
        "s_1191"
      ],
      "lp_norm": 0.6547942261109497,
      "cost": 2759.0,
      "reward": 627.0,
      "prestige": 1.0,
      "score": 0.7878810119552738
    },
    {
      "agent": "EDU",
      "size": "L",
      "footprint_slots": [
        "s_1234"
      ],
      "lp_norm": 0.6774430216435886,
      "cost": 2781.0,
      "reward": 627.0,
      "prestige": 1.0,
      "score": 0.786453367568512
    },
    {
      "agent": "EDU",
      "size": "L",
      "footprint_slots": [
        "s_1307"
      ],
      "lp_norm": 0.7555287345590923,
      "cost": 2858.0,
      "reward": 636.0,
      "prestige": 1.0,
      "score": 0.7911921891379224
    },
    {
      "agent": "EDU",
      "size": "L",
      "footprint_slots": [
        "s_1331"
      ],
      "lp_norm": 0.6946271647150053,
      "cost": 2803.0,
      "reward": 633.0,
      "prestige": 1.0,
      "score": 0.7915161077971347
    },
    {
      "agent": "EDU",
      "size": "L",
      "footprint_slots": [
        "s_1056"
      ],
      "lp_norm": 0.7264550306304726,
      "cost": 2825.0,
      "reward": 633.0,
      "prestige": 1.0,
      "score": 0.7900884634103729
    },
    {
      "agent": "EDU",
      "size": "L",
      "footprint_slots": [
        "s_1403"
      ],
      "lp_norm": 0.7043997187030165,
      "cost": 2803.0,
      "reward": 632.0,
      "prestige": 1.0,
      "score": 0.7904343770279039
    },
    {
      "agent": "EDU",
      "size": "L",
      "footprint_slots": [
        "s_1327"
      ],
      "lp_norm": 0.8402877350859839,
      "cost": 2946.0,
      "reward": 641.0,
      "prestige": 1.0,
      "score": 0.7908902654370289
    },
    {
      "agent": "EDU",
      "size": "L",
      "footprint_slots": [
        "s_1042"
      ],
      "lp_norm": 0.6697545474172746,
      "cost": 2770.0,
      "reward": 629.0,
      "prestige": 1.0,
      "score": 0.7893306513003545
    },
    {
      "agent": "EDU",
      "size": "L",
      "footprint_slots": [
        "s_1213"
      ],
      "lp_norm": 0.855875096300516,
      "cost": 2957.0,
      "reward": 641.0,
      "prestige": 1.0,
      "score": 0.790176443243648
    },
    {
      "agent": "EDU",
      "size": "L",
      "footprint_slots": [
        "s_1399"
      ],
      "lp_norm": 0.6988822294234964,
      "cost": 2803.0,
      "reward": 629.0,
      "prestige": 1.0,
      "score": 0.7871891847202117
    },
    {
      "agent": "EDU",
      "size": "L",
      "footprint_slots": [
        "s_1185"
      ],
      "lp_norm": 0.811107934011535,
      "cost": 2913.0,
      "reward": 637.0,
      "prestige": 1.0,
      "score": 0.7887048089402486
    },
    {
      "agent": "EDU",
      "size": "L",
      "footprint_slots": [
        "s_1374"
      ],
      "lp_norm": 0.7894735595301646,
      "cost": 2891.0,
      "reward": 637.0,
      "prestige": 1.0,
      "score": 0.7901324533270105
    },
    {
      "agent": "EDU",
      "size": "L",
      "footprint_slots": [
        "s_1003"
      ],
      "lp_norm": 0.7947917810413252,
      "cost": 2902.0,
      "reward": 638.0,
      "prestige": 1.0,
      "score": 0.7905003619028603
    },
    {
      "agent": "EDU",
      "size": "L",
      "footprint_slots": [
        "s_1349"
      ],
      "lp_norm": 0.7367696887553298,
      "cost": 2836.0,
      "reward": 634.0,
      "prestige": 1.0,
      "score": 0.7904563719862228
    },
    {
      "agent": "EDU",
      "size": "L",
      "footprint_slots": [
        "s_955"
      ],
      "lp_norm": 0.7652887852882968,
      "cost": 2869.0,
      "reward": 637.0,
      "prestige": 1.0,
      "score": 0.7915600977137723
    },
    {
      "agent": "EDU",
      "size": "L",
      "footprint_slots": [
        "s_1012"
      ],
      "lp_norm": 0.7544534402824742,
      "cost": 2858.0,
      "reward": 633.0,
      "prestige": 1.0,
      "score": 0.7879469968302301
    },
    {
      "agent": "EDU",
      "size": "L",
      "footprint_slots": [
        "s_1324"
      ],
      "lp_norm": 0.8287564432704952,
      "cost": 2935.0,
      "reward": 640.0,
      "prestige": 1.0,
      "score": 0.7905223568611791
    },
    {
      "agent": "EDU",
      "size": "L",
      "footprint_slots": [
        "s_1352"
      ],
      "lp_norm": 0.7975882263094929,
      "cost": 2902.0,
      "reward": 636.0,
      "prestige": 1.0,
      "score": 0.7883369003643987
    },
    {
      "agent": "EDU",
      "size": "L",
      "footprint_slots": [
        "s_1210"
      ],
      "lp_norm": 0.80985577176689,
      "cost": 2913.0,
      "reward": 638.0,
      "prestige": 1.0,
      "score": 0.7897865397094793
    },
    {
      "agent": "EDU",
      "size": "L",
      "footprint_slots": [
        "s_1160"
      ],
      "lp_norm": 0.8554594704995576,
      "cost": 2957.0,
      "reward": 642.0,
      "prestige": 1.0,
      "score": 0.7912581740128787
    },
    {
      "agent": "EDU",
      "size": "L",
      "footprint_slots": [
        "s_1220"
      ],
      "lp_norm": 0.7837392543078846,
      "cost": 2891.0,
      "reward": 636.0,
      "prestige": 1.0,
      "score": 0.7890507225577797
    },
    {
      "agent": "EDU",
      "size": "L",
      "footprint_slots": [
        "s_1390"
      ],
      "lp_norm": 0.7297415440274295,
      "cost": 2836.0,
      "reward": 631.0,
      "prestige": 1.0,
      "score": 0.7872111796785305
    },
    {
      "agent": "EDU",
      "size": "L",
      "footprint_slots": [
        "s_1389"
      ],
      "lp_norm": 0.6794700727934657,
      "cost": 2781.0,
      "reward": 631.0,
      "prestige": 1.0,
      "score": 0.7907802906454351
    },
    {
      "agent": "EDU",
      "size": "L",
      "footprint_slots": [
        "s_1144"
      ],
      "lp_norm": 0.8282062525655072,
      "cost": 2935.0,
      "reward": 640.0,
      "prestige": 1.0,
      "score": 0.7905223568611791
    },
    {
      "agent": "EDU",
      "size": "L",
      "footprint_slots": [
        "s_1345"
      ],
      "lp_norm": 0.792035721926859,
      "cost": 2891.0,
      "reward": 638.0,
      "prestige": 1.0,
      "score": 0.7912141840962412
    },
    {
      "agent": "EDU",
      "size": "L",
      "footprint_slots": [
        "s_1381"
      ],
      "lp_norm": 0.7722180175970745,
      "cost": 2869.0,
      "reward": 636.0,
      "prestige": 1.0,
      "score": 0.7904783669445415
    },
    {
      "agent": "EDU",
      "size": "L",
      "footprint_slots": [
        "s_1037"
      ],
      "lp_norm": 0.6766832318602001,
      "cost": 2781.0,
      "reward": 629.0,
      "prestige": 1.0,
      "score": 0.7886168291069736
    },
    {
      "agent": "EDU",
      "size": "L",
      "footprint_slots": [
        "s_1155"
      ],
      "lp_norm": 0.8691147621599544,
      "cost": 2968.0,
      "reward": 643.0,
      "prestige": 1.0,
      "score": 0.7916260825887286
    },
    {
      "agent": "EDU",
      "size": "L",
      "footprint_slots": [
        "s_1029"
      ],
      "lp_norm": 0.7155966118861543,
      "cost": 2814.0,
      "reward": 633.0,
      "prestige": 1.0,
      "score": 0.7908022856037538
    },
    {
      "agent": "EDU",
      "size": "L",
      "footprint_slots": [
        "s_1032"
      ],
      "lp_norm": 0.6757593131795081,
      "cost": 2781.0,
      "reward": 630.0,
      "prestige": 1.0,
      "score": 0.7896985598762043
    },
    {
      "agent": "EDU",
      "size": "L",
      "footprint_slots": [
        "s_1292"
      ],
      "lp_norm": 0.855412260381711,
      "cost": 2957.0,
      "reward": 642.0,
      "prestige": 1.0,
      "score": 0.7912581740128787
    },
    {
      "agent": "EDU",
      "size": "L",
      "footprint_slots": [
        "s_1147"
      ],
      "lp_norm": 0.8565415811451867,
      "cost": 2957.0,
      "reward": 642.0,
      "prestige": 1.0,
      "score": 0.7912581740128787
    },
    {
      "agent": "EDU",
      "size": "L",
      "footprint_slots": [
        "s_1541"
      ],
      "lp_norm": 0.6783115493273695,
      "cost": 2781.0,
      "reward": 632.0,
      "prestige": 1.0,
      "score": 0.7918620214146658
    },
    {
      "agent": "EDU",
      "size": "L",
      "footprint_slots": [
        "s_1355"
      ],
      "lp_norm": 0.7203387332080297,
      "cost": 2825.0,
      "reward": 631.0,
      "prestige": 1.0,
      "score": 0.7879250018719114
    },
    {
      "agent": "EDU",
      "size": "L",
      "footprint_slots": [
        "s_1181"
      ],
      "lp_norm": 0.8063134278052271,
      "cost": 2913.0,
      "reward": 638.0,
      "prestige": 1.0,
      "score": 0.7897865397094793
    },
    {
      "agent": "EDU",
      "size": "L",
      "footprint_slots": [
        "s_1175"
      ],
      "lp_norm": 0.886548093431764,
      "cost": 2990.0,
      "reward": 644.0,
      "prestige": 1.0,
      "score": 0.7912801689711976
    },
    {
      "agent": "EDU",
      "size": "L",
      "footprint_slots": [
        "s_1383"
      ],
      "lp_norm": 0.6769311713908425,
      "cost": 2781.0,
      "reward": 627.0,
      "prestige": 1.0,
      "score": 0.786453367568512
    },
    {
      "agent": "EDU",
      "size": "L",
      "footprint_slots": [
        "s_1126"
      ],
      "lp_norm": 0.8795879730474611,
      "cost": 2979.0,
      "reward": 643.0,
      "prestige": 1.0,
      "score": 0.7909122603953477
    },
    {
      "agent": "EDU",
      "size": "L",
      "footprint_slots": [
        "s_1054"
      ],
      "lp_norm": 0.7832115888686615,
      "cost": 2880.0,
      "reward": 637.0,
      "prestige": 1.0,
      "score": 0.7908462755203914
    },
    {
      "agent": "EDU",
      "size": "L",
      "footprint_slots": [
        "s_1214"
      ],
      "lp_norm": 0.7873641966486756,
      "cost": 2891.0,
      "reward": 635.0,
      "prestige": 1.0,
      "score": 0.787968991788549
    },
    {
      "agent": "EDU",
      "size": "L",
      "footprint_slots": [
        "s_1488"
      ],
      "lp_norm": 0.656011598378926,
      "cost": 2759.0,
      "reward": 630.0,
      "prestige": 1.0,
      "score": 0.7911262042629661
    },
    {
      "agent": "EDU",
      "size": "L",
      "footprint_slots": [
        "s_1203"
      ],
      "lp_norm": 0.6590590756676202,
      "cost": 2759.0,
      "reward": 626.0,
      "prestige": 1.0,
      "score": 0.786799281186043
    },
    {
      "agent": "EDU",
      "size": "L",
      "footprint_slots": [
        "s_1186"
      ],
      "lp_norm": 0.8263348287063033,
      "cost": 2924.0,
      "reward": 639.0,
      "prestige": 1.0,
      "score": 0.7901544482853293
    },
    {
      "agent": "EDU",
      "size": "L",
      "footprint_slots": [
        "s_1379"
      ],
      "lp_norm": 0.7562315142118713,
      "cost": 2858.0,
      "reward": 635.0,
      "prestige": 1.0,
      "score": 0.7901104583686916
    },
    {
      "agent": "EDU",
      "size": "L",
      "footprint_slots": [
        "s_1405"
      ],
      "lp_norm": 0.6639062995339491,
      "cost": 2770.0,
      "reward": 628.0,
      "prestige": 1.0,
      "score": 0.7882489205311237
    },
    {
      "agent": "EDU",
      "size": "L",
      "footprint_slots": [
        "s_1223"
      ],
      "lp_norm": 0.8285127165378043,
      "cost": 2935.0,
      "reward": 638.0,
      "prestige": 1.0,
      "score": 0.7883588953227175
    },
    {
      "agent": "EDU",
      "size": "L",
      "footprint_slots": [
        "s_1050"
      ],
      "lp_norm": 0.7489873621946224,
      "cost": 2847.0,
      "reward": 635.0,
      "prestige": 1.0,
      "score": 0.7908242805620727
    },
    {
      "agent": "EDU",
      "size": "L",
      "footprint_slots": [
        "s_1217"
      ],
      "lp_norm": 0.8490228007501379,
      "cost": 2946.0,
      "reward": 641.0,
      "prestige": 1.0,
      "score": 0.7908902654370289
    },
    {
      "agent": "EDU",
      "size": "L",
      "footprint_slots": [
        "s_1502"
      ],
      "lp_norm": 0.6473418205683608,
      "cost": 2748.0,
      "reward": 633.0,
      "prestige": 1.0,
      "score": 0.7950852187640394
    },
    {
      "agent": "EDU",
      "size": "L",
      "footprint_slots": [
        "s_1216"
      ],
      "lp_norm": 0.8477008676787294,
      "cost": 2946.0,
      "reward": 639.0,
      "prestige": 1.0,
      "score": 0.7887268038985675
    },
    {
      "agent": "EDU",
      "size": "L",
      "footprint_slots": [
        "s_1182"
      ],
      "lp_norm": 0.7594183759256643,
      "cost": 2858.0,
      "reward": 633.0,
      "prestige": 1.0,
      "score": 0.7879469968302301
    },
    {
      "agent": "EDU",
      "size": "L",
      "footprint_slots": [
        "s_1027"
      ],
      "lp_norm": 0.735125810439303,
      "cost": 2836.0,
      "reward": 634.0,
      "prestige": 1.0,
      "score": 0.7904563719862228
    },
    {
      "agent": "EDU",
      "size": "L",
      "footprint_slots": [
        "s_1353"
      ],
      "lp_norm": 0.678149627761237,
      "cost": 2781.0,
      "reward": 628.0,
      "prestige": 1.0,
      "score": 0.7875350983377428
    },
    {
      "agent": "EDU",
      "size": "L",
      "footprint_slots": [
        "s_1404"
      ],
      "lp_norm": 0.6925897232340035,
      "cost": 2792.0,
      "reward": 631.0,
      "prestige": 1.0,
      "score": 0.7900664684520542
    },
    {
      "agent": "EDU",
      "size": "L",
      "footprint_slots": [
        "s_1357"
      ],
      "lp_norm": 0.7780253740444703,
      "cost": 2880.0,
      "reward": 636.0,
      "prestige": 1.0,
      "score": 0.7897645447511606
    },
    {
      "agent": "EDU",
      "size": "L",
      "footprint_slots": [
        "s_1360"
      ],
      "lp_norm": 0.7202601619239161,
      "cost": 2825.0,
      "reward": 632.0,
      "prestige": 1.0,
      "score": 0.7890067326411421
    },
    {
      "agent": "EDU",
      "size": "L",
      "footprint_slots": [
        "s_1362"
      ],
      "lp_norm": 0.8425577470915846,
      "cost": 2946.0,
      "reward": 640.0,
      "prestige": 1.0,
      "score": 0.7898085346677981
    },
    {
      "agent": "EDU",
      "size": "L",
      "footprint_slots": [
        "s_1005"
      ],
      "lp_norm": 0.67899952675558,
      "cost": 2781.0,
      "reward": 632.0,
      "prestige": 1.0,
      "score": 0.7918620214146658
    },
    {
      "agent": "EDU",
      "size": "L",
      "footprint_slots": [
        "s_1358"
      ],
      "lp_norm": 0.8346858005218297,
      "cost": 2935.0,
      "reward": 640.0,
      "prestige": 1.0,
      "score": 0.7905223568611791
    },
    {
      "agent": "EDU",
      "size": "L",
      "footprint_slots": [
        "s_1411"
      ],
      "lp_norm": 0.6724213937172416,
      "cost": 2781.0,
      "reward": 627.0,
      "prestige": 1.0,
      "score": 0.786453367568512
    },
    {
      "agent": "EDU",
      "size": "L",
      "footprint_slots": [
        "s_1368"
      ],
      "lp_norm": 0.7374011059236654,
      "cost": 2836.0,
      "reward": 632.0,
      "prestige": 1.0,
      "score": 0.7882929104477612
    },
    {
      "agent": "EDU",
      "size": "L",
      "footprint_slots": [
        "s_1384"
      ],
      "lp_norm": 0.7045934466136099,
      "cost": 2803.0,
      "reward": 630.0,
      "prestige": 1.0,
      "score": 0.7882709154894424
    },
    {
      "agent": "EDU",
      "size": "L",
      "footprint_slots": [
        "s_992"
      ],
      "lp_norm": 0.7111088907632295,
      "cost": 2814.0,
      "reward": 634.0,
      "prestige": 1.0,
      "score": 0.7918840163729846
    },
    {
      "agent": "EDU",
      "size": "L",
      "footprint_slots": [
        "s_1334"
      ],
      "lp_norm": 0.7368768972170006,
      "cost": 2836.0,
      "reward": 635.0,
      "prestige": 1.0,
      "score": 0.7915381027554536
    },
    {
      "agent": "EDU",
      "size": "L",
      "footprint_slots": [
        "s_1190"
      ],
      "lp_norm": 0.6546948728260229,
      "cost": 2759.0,
      "reward": 625.0,
      "prestige": 1.0,
      "score": 0.7857175504168122
    },
    {
      "agent": "EDU",
      "size": "L",
      "footprint_slots": [
        "s_1332"
      ],
      "lp_norm": 0.8185395828933737,
      "cost": 2924.0,
      "reward": 640.0,
      "prestige": 1.0,
      "score": 0.79123617905456
    },
    {
      "agent": "EDU",
      "size": "L",
      "footprint_slots": [
        "s_1195"
      ],
      "lp_norm": 0.7847619642065327,
      "cost": 2891.0,
      "reward": 637.0,
      "prestige": 1.0,
      "score": 0.7901324533270105
    }
  ],
  "active_agent": "EDU"
}