{
  "month": 245,
  "count": 30,
  "sequences": [
    {
      "score": 0.23199653193016023,
      "actions": [
        {
          "agent": "IND",
          "size": "S",
          "footprint_slots": [
            "s_607"
          ],
          "score": 0.23199653193016023
        }
      ]
    },
    {
      "score": 0.23198696484094716,
      "actions": [
        {
          "agent": "IND",
          "size": "S",
          "footprint_slots": [
            "s_819"
          ],
          "score": 0.23198696484094716
        }
      ]
    },
    {
      "score": 0.23160846687395362,
      "actions": [
        {
          "agent": "IND",
          "size": "S",
          "footprint_slots": [
            "s_351"
          ],
          "score": 0.23160846687395362
        }
      ]
    },
    {
      "score": 0.23160368332934708,
      "actions": [
        {
          "agent": "IND",
          "size": "S",
          "footprint_slots": [
            "s_480"
          ],
          "score": 0.23160368332934708
        }
      ]
    },
    {
      "score": 0.2315988997847405,
      "actions": [
        {
          "agent": "IND",
          "size": "S",
          "footprint_slots": [
            "s_126"
          ],
          "score": 0.2315988997847405
        }
      ]
    },
    {
      "score": 0.2315893326955274,
      "actions": [
        {
          "agent": "IND",
          "size": "S",
          "footprint_slots": [
            "s_618"
          ],
          "score": 0.2315893326955274
        }
      ]
    },
    {
      "score": 0.2315893326955274,
      "actions": [
        {
          "agent": "IND",
          "size": "S",
          "footprint_slots": [
            "s_155"
          ],
          "score": 0.2315893326955274
        }
      ]
    },
    {
      "score": 0.23158454915092086,
      "actions": [
        {
          "agent": "IND",
          "size": "S",
          "footprint_slots": [
            "s_181"
          ],
          "score": 0.23158454915092086
        }
      ]
    },
    {
      "score": 0.23158454915092086,
      "actions": [
        {
          "agent": "IND",
          "size": "S",
          "footprint_slots": [
            "s_172"
          ],
          "score": 0.23158454915092086
        }
      ]
    },
    {
      "score": 0.23118213346089456,
      "actions": [
        {
          "agent": "IND",
          "size": "S",
          "footprint_slots": [
            "s_168"
          ],
          "score": 0.23118213346089456
        }
      ]
    },
    {
      "score": 0.4639834967711074,
      "actions": [
        {
          "agent": "IND",
          "size": "S",
          "footprint_slots": [
            "s_607"
          ],
          "score": 0.23199653193016023
        },
        {
          "agent": "IND",
          "size": "S",
          "footprint_slots": [
            "s_819"
          ],
          "score": 0.23198696484094716
        }
      ]
    },
    {
      "score": 0.4636049988041139,
      "actions": [
        {
          "agent": "IND",
          "size": "S",
          "footprint_slots": [
            "s_607"
          ],
          "score": 0.23199653193016023
        },
        {
          "agent": "IND",
          "size": "S",
          "footprint_slots": [
            "s_351"
          ],
          "score": 0.23160846687395362
        }
      ]
    },
    {
      "score": 0.46360021525950734,
      "actions": [
        {
          "agent": "IND",
          "size": "S",
          "footprint_slots": [
            "s_607"
          ],
          "score": 0.23199653193016023
        },
        {
          "agent": "IND",
          "size": "S",
          "footprint_slots": [
            "s_480"
          ],
          "score": 0.23160368332934708
        }
      ]
    },
    {
      "score": 0.4635954317149008,
      "actions": [
        {
          "agent": "IND",
          "size": "S",
          "footprint_slots": [
            "s_819"
          ],
          "score": 0.23198696484094716
        },
        {
          "agent": "IND",
          "size": "S",
          "footprint_slots": [
            "s_351"
          ],
          "score": 0.23160846687395362
        }
      ]
    },
    {
      "score": 0.4635954317149007,
      "actions": [
        {
          "agent": "IND",
          "size": "S",
          "footprint_slots": [
            "s_607"
          ],
          "score": 0.23199653193016023
        },
        {
          "agent": "IND",
          "size": "S",
          "footprint_slots": [
            "s_126"
          ],
          "score": 0.2315988997847405
        }
      ]
    },
    {
      "score": 0.4635906481702943,
      "actions": [
        {
          "agent": "IND",
          "size": "S",
          "footprint_slots": [
            "s_819"
          ],
          "score": 0.23198696484094716
        },
        {
          "agent": "IND",
          "size": "S",
          "footprint_slots": [
            "s_480"
          ],
          "score": 0.23160368332934708
        }
      ]
    },
    {
      "score": 0.4635858646256876,
      "actions": [
        {
          "agent": "IND",
          "size": "S",
          "footprint_slots": [
            "s_607"
          ],
          "score": 0.23199653193016023
        },
        {
          "agent": "IND",
          "size": "S",
          "footprint_slots": [
            "s_618"
          ],
          "score": 0.2315893326955274
        }
      ]
    },
    {
      "score": 0.4635858646256876,
      "actions": [
        {
          "agent": "IND",
          "size": "S",
          "footprint_slots": [
            "s_607"
          ],
          "score": 0.23199653193016023
        },
        {
          "agent": "IND",
          "size": "S",
          "footprint_slots": [
            "s_155"
          ],
          "score": 0.2315893326955274
        }
      ]
    },
    {
      "score": 0.4635858646256876,
      "actions": [
        {
          "agent": "IND",
          "size": "S",
          "footprint_slots": [
            "s_819"
          ],
          "score": 0.23198696484094716
        },
        {
          "agent": "IND",
          "size": "S",
          "footprint_slots": [
            "s_126"
          ],
          "score": 0.2315988997847405
        }
      ]
    },
    {
      "score": 0.4635810810810811,
      "actions": [
        {
          "agent": "IND",
          "size": "S",
          "footprint_slots": [
            "s_607"
          ],
          "score": 0.23199653193016023
        },
        {
          "agent": "IND",
          "size": "S",
          "footprint_slots": [
            "s_181"
          ],
          "score": 0.23158454915092086
        }
      ]
    },
    {
      "score": 0.695591963645061,
      "actions": [
        {
          "agent": "IND",
          "size": "S",
          "footprint_slots": [
            "s_607"
          ],
          "score": 0.23199653193016023
        },
        {
          "agent": "IND",
          "size": "S",
          "footprint_slots": [
            "s_819"
          ],
          "score": 0.23198696484094716
        },
        {
          "agent": "IND",
          "size": "S",
          "footprint_slots": [
            "s_351"
          ],
          "score": 0.23160846687395362
        }
      ]
    },
    {
      "score": 0.6955871801004545,
      "actions": [
        {
          "agent": "IND",
          "size": "S",
          "footprint_slots": [
            "s_607"
          ],
          "score": 0.23199653193016023
        },
        {
          "agent": "IND",
          "size": "S",
          "footprint_slots": [
            "s_819"
          ],
          "score": 0.23198696484094716
        },
        {
          "agent": "IND",
          "size": "S",
          "footprint_slots": [
            "s_480"
          ],
          "score": 0.23160368332934708
        }
      ]
    },
    {
      "score": 0.6955823965558479,
      "actions": [
        {
          "agent": "IND",
          "size": "S",
          "footprint_slots": [
            "s_607"
          ],
          "score": 0.23199653193016023
        },
        {
          "agent": "IND",
          "size": "S",
          "footprint_slots": [
            "s_819"
          ],
          "score": 0.23198696484094716
        },
        {
          "agent": "IND",
          "size": "S",
          "footprint_slots": [
            "s_126"
          ],
          "score": 0.2315988997847405
        }
      ]
    },
    {
      "score": 0.6955728294666348,
      "actions": [
        {
          "agent": "IND",
          "size": "S",
          "footprint_slots": [
            "s_607"
          ],
          "score": 0.23199653193016023
        },
        {
          "agent": "IND",
          "size": "S",
          "footprint_slots": [
            "s_819"
          ],
          "score": 0.23198696484094716
        },
        {
          "agent": "IND",
          "size": "S",
          "footprint_slots": [
            "s_618"
          ],
          "score": 0.2315893326955274
        }
      ]
    },
    {
      "score": 0.6955728294666348,
      "actions": [
        {
          "agent": "IND",
          "size": "S",
          "footprint_slots": [
            "s_607"
          ],
          "score": 0.23199653193016023
        },
        {
          "agent": "IND",
          "size": "S",
          "footprint_slots": [
            "s_819"
          ],
          "score": 0.23198696484094716
        },
        {
          "agent": "IND",
          "size": "S",
          "footprint_slots": [
            "s_155"
          ],
          "score": 0.2315893326955274
        }
      ]
    },
    {
      "score": 0.6955680459220283,
      "actions": [
        {
          "agent": "IND",
          "size": "S",
          "footprint_slots": [
            "s_607"
          ],
          "score": 0.23199653193016023
        },
        {
          "agent": "IND",
          "size": "S",
          "footprint_slots": [
            "s_819"
          ],
          "score": 0.23198696484094716
        },
        {
          "agent": "IND",
          "size": "S",
          "footprint_slots": [
            "s_181"
          ],
          "score": 0.23158454915092086
        }
      ]
    },
    {
      "score": 0.6955680459220283,
      "actions": [
        {
          "agent": "IND",
          "size": "S",
          "footprint_slots": [
            "s_607"
          ],
          "score": 0.23199653193016023
        },
        {
          "agent": "IND",
          "size": "S",
          "footprint_slots": [
            "s_819"
          ],
          "score": 0.23198696484094716
        },
        {
          "agent": "IND",
          "size": "S",
          "footprint_slots": [
            "s_172"
          ],
          "score": 0.23158454915092086
        }
      ]
    },
    {
      "score": 0.695208682133461,
      "actions": [
        {
          "agent": "IND",
          "size": "S",
          "footprint_slots": [
            "s_607"
          ],
          "score": 0.23199653193016023
        },
        {
          "agent": "IND",
          "size": "S",
          "footprint_slots": [
            "s_351"
          ],
          "score": 0.23160846687395362
        },
        {
          "agent": "IND",
          "size": "S",
          "footprint_slots": [
            "s_480"
          ],
          "score": 0.23160368332934708
        }
      ]
    },
    {
      "score": 0.6952038985888543,
      "actions": [
        {
          "agent": "IND",
          "size": "S",
          "footprint_slots": [
            "s_607"
          ],
          "score": 0.23199653193016023
        },
        {
          "agent": "IND",
          "size": "S",
          "footprint_slots": [
            "s_351"
          ],
          "score": 0.23160846687395362
        },
        {
          "agent": "IND",
          "size": "S",
          "footprint_slots": [
            "s_126"
          ],
          "score": 0.2315988997847405
        }
      ]
    },
    {
      "score": 0.6951991150442479,
      "actions": [
        {
          "agent": "IND",
          "size": "S",
          "footprint_slots": [
            "s_819"
          ],
          "score": 0.23198696484094716
        },
        {
          "agent": "IND",
          "size": "S",
          "footprint_slots": [
            "s_351"
          ],
          "score": 0.23160846687395362
        },
        {
          "agent": "IND",
          "size": "S",
          "footprint_slots": [
            "s_480"
          ],
          "score": 0.23160368332934708
        }
      ]
    }
  ],
  "debug": {
    "layers": [
      {
        "beam_in": 50,
        "non_conflict_min": 400,
        "non_conflict_max": 400,
        "non_conflict_avg": 400.0,
        "new_beam_kept": 50,
        "expansions_used": 400
      },
      {
        "beam_in": 50,
        "non_conflict_min": 399,
        "non_conflict_max": 399,
        "non_conflict_avg": 399.0,
        "new_beam_kept": 50,
        "expansions_used": 20350
      },
      {
        "beam_in": 50,
        "non_conflict_min": 98,
        "non_conflict_max": 398,
        "non_conflict_avg": 386.0,
        "new_beam_kept": 50,
        "expansions_used": 30000
      }
    ],
    "stopped": "max_expansions",
    "stratified": {
      "enabled": true,
      "per_depth": 10,
      "counts": {
        "1": 10,
        "2": 10,
        "3": 10,
        "4": 0,
        "5": 0
      }
    }
  },
  "active_agent": "IND"
}